Workbook
Name Slicer_charges: #N/A
Name Slicer_Customer_ID: #N/A
Name Slicer_Diabetes_Status: #N/A
Name Slicer_Number_Of_Major_Surgeries: #N/A
Name Slicer_smoker: #N/A
Name Slicer_Weight_Status: #N/A

Sheet Customer Names
A1: Customer ID | B1: Name | C1: Title | D1: First Name | E1: Last Name
A2: Id1 | B2: Hawks, Ms. Kelly | C2: Ms | D2: Kelly | E2: Hawks
A3: Id2 | B3: Lehner, Mr. Matthew D | C3: Mr | D3: Matthew D | E3: Lehner
A4: Id3 | B4: Lu, Mr. Phil | C4: Mr | D4: Phil | E4: Lu
A5: Id4 | B5: Osborne, Ms. Kelsey | C5: Ms | D5: Kelsey | E5: Osborne
A6: Id5 | B6: Kadala, Ms. Kristyn | C6: Ms | D6: Kristyn | E6: Kadala
A7: Id6 | B7: Baker, Mr. Russell B. | C7: Mr | D7: Russell B | E7: Baker
A8: Id7 | B8: Macpherson, Mr. Scott | C8: Mr | D8: Scott | E8: Macpherson
A9: Id8 | B9: Hallman, Mr. Stephen | C9: Mr | D9: Stephen | E9: Hallman
A10: Id9 | B10: Moran, Mr. Patrick R. | C10: Mr | D10: Patrick R | E10: Moran
A11: Id10 | B11: Benner, Ms. Brooke N. | C11: Ms | D11: Brooke N | E11: Benner
A12: Id11 | B12: Fierro Vargas, Ms. Paola Andrea | C12: Ms | D12: Paola Andrea | E12: Fierro Vargas
... A72: Id71 | B72: Turner, Mr. Jeff | C72: Mr | D72: Jeff | E72: Turner
A73: Id72 | B73: Rangel, Mr. Elenilton V. Sr. | C73: Mr | D73: Elenilton V | E73: Rangel | H73: Sr
A74: Id73 | B74: Lacey, Ms. Maurya | C74: Ms | D74: Maurya | E74: Lacey
A75: Id74 | B75: Stiger, Ms. Samantha C | C75: Ms | D75: Samantha C | E75: Stiger
A76: Id75 | B76: Caldwell, Ms. Bethany A | C76: Ms | D76: Bethany A | E76: Caldwell
A77: Id76 | B77: Marmillod, Mr. Yves | C77: Mr | D77: Yves | E77: Marmillod
A78: Id77 | B78: Cloutier-Simons, Ms. Danielle | C78: Ms | D78: Danielle | E78: Cloutier-Simons
A79: Id78 | B79: Vegas, Ms. Julia | C79: Ms | D79: Julia | E79: Vegas
A80: Id79 | B80: Cochran, Mr. Joshua | C80: Mr | D80: Joshua | E80: Cochran
A81: Id80 | B81: Holtzapple, Ms. Jennifer | C81: Ms | D81: Jennifer | E81: Holtzapple
A82: Id81 | B82: Meyer, Ms. Gwen M. | C82: Ms | D82: Gwen M | E82: Meyer
A83: Id82 | B83: Brickley, Mr. Patrick | C83: Mr | D83: Patrick | E83: Brickley
A84: Id83 | B84: Magee, Ms. Kate | C84: Ms | D84: Kate | E84: Magee
A85: Id84 | B85: Thoma, Mr. Kevin | C85: Mr | D85: Kevin | E85: Thoma
... A188: Id187 | B188: Dublin, Mr. Andrew P | C188: Mr | D188: Andrew P | E188: Dublin
A189: Id188 | B189: Cleland, Mr. George M. V | C189: Mr | D189: George M | E189: Cleland | H189: V
A190: Id189 | B190: Evans, Ms. Sarah | C190: Ms | D190: Sarah | E190: Evans
A191: Id190 | B191: Boyd, Ms. Lara | C191: Ms | D191: Lara | E191: Boyd
A192: Id191 | B192: Roulier, Mr. Sebastien | C192: Mr | D192: Sebastien | E192: Roulier
A193: Id192 | B193: Mullins, Mr. Padraig | C193: Mr | D193: Padraig | E193: Mullins
A194: Id193 | B194: Hofmann, Ms. Heather | C194: Ms | D194: Heather | E194: Hofmann
A195: Id194 | B195: Garcia Garcia, Mr. Jorge | C195: Mr | D195: Jorge | E195: Garcia Garcia
A196: Id195 | B196: Klecker, Mr. Jack R | C196: Mr | D196: Jack R | E196: Klecker
A197: Id196 | B197: Cancre, Mr. Felix | C197: Mr | D197: Felix | E197: Cancre
A198: Id197 | B198: Denucci, Mr. Christopher C | C198: Mr | D198: Christopher C | E198: Denucci
A199: Id198 | B199: Saldana, Mr. Jesse | C199: Mr | D199: Jesse | E199: Saldana
A200: Id199 | B200: Weinberg, Ms. Jill | C200: Ms | D200: Jill | E200: Weinberg
A201: Id200 | B201: Walsh, Mr. William | C201: Mr | D201: William | E201: Walsh
... A476: Id475 | B476: Narang, Mr. Jatin | C476: Mr | D476: Jatin | E476: Narang
A477: Id476 | B477: Royston, Mr. J P. Ii | C477: Mr | D477: J P | E477: Royston | H477: Ii
A478: Id477 | B478: Tieri, Ms. Angela M. | C478: Ms | D478: Angela M | E478: Tieri
A479: Id478 | B479: Whitney, Mr. Blake K. | C479: Mr | D479: Blake K | E479: Whitney
A480: Id479 | B480: Wandzilak, Mr. Brian T. | C480: Mr | D480: Brian T | E480: Wandzilak
A481: Id480 | B481: Valenzona, Mr. Damon | C481: Mr | D481: Damon | E481: Valenzona
A482: Id481 | B482: Young, Mr. Jeffrey | C482: Mr | D482: Jeffrey | E482: Young
A483: Id482 | B483: Richards, Mr. Malcolm J. | C483: Mr | D483: Malcolm J | E483: Richards
A484: Id483 | B484: Alexson, Ms. Margaret B. | C484: Ms | D484: Margaret B | E484: Alexson
A485: Id484 | B485: Wright, Ms. Helen | C485: Ms | D485: Helen | E485: Wright
A486: Id485 | B486: Mckenna, Mr. Matthew | C486: Mr | D486: Matthew | E486: Mckenna
A487: Id486 | B487: Sallade, Mr. Jeff | C487: Mr | D487: Jeff | E487: Sallade
A488: Id487 | B488: Argall, Mrs. Tara R | C488: Mrs | D488: Tara R | E488: Argall
A489: Id488 | B489: Patchell, Ms. Kristin | C489: Ms | D489: Kristin | E489: Patchell
... A725: Id724 | B725: Nemec, Mrs. Lisa | C725: Mrs | D725: Lisa | E725: Nemec
A726: Id725 | B726: Appman, Mr. William D. Jr. | C726: Mr | D726: William D | E726: Appman | H726: Jr
A727: Id726 | B727: Driscoll, Mr. James | C727: Mr | D727: James | E727: Driscoll
A728: Id727 | B728: Glotzbach, Mr. John | C728: Mr | D728: John | E728: Glotzbach
A729: Id728 | B729: Tenforde, Mr. Adam S | C729: Mr | D729: Adam S | E729: Tenforde
A730: Id729 | B730: Ramirez, Mr. Armando | C730: Mr | D730: Armando | E730: Ramirez
A731: Id730 | B731: Stanley Torres, Ms. Dana | C731: Ms | D731: Dana | E731: Stanley Torres
A732: Id731 | B732: Vandongen, Ms. Jennifer L | C732: Ms | D732: Jennifer L | E732: Vandongen
A733: Id732 | B733: Liebald, Mr. Benjamin | C733: Mr | D733: Benjamin | E733: Liebald
A734: Id733 | B734: Holte, Ms. Tanya | C734: Ms | D734: Tanya | E734: Holte
A735: Id734 | B735: Johnson, Ms. Tracy | C735: Ms | D735: Tracy | E735: Johnson
A736: Id735 | B736: Bartlett, Ms. Emily S | C736: Ms | D736: Emily S | E736: Bartlett
A737: Id736 | B737: Bergman, Ms. Kelly R | C737: Ms | D737: Kelly R | E737: Bergman
A738: Id737 | B738: Aitken, Mr. Kyle | C738: Mr | D738: Kyle | E738: Aitken
... A892: Id891 | B892: Bauder, Mr. Andrew R | C892: Mr | D892: Andrew R | E892: Bauder
A893: Id892 | B893: Mendoza, Mr. Francisco J. Sr. | C893: Mr | D893: Francisco J | E893: Mendoza | H893: Sr
A894: Id893 | B894: Glass, Mrs. Rhonda | C894: Mrs | D894: Rhonda | E894: Glass
A895: Id894 | B895: Butcher, Mr. John | C895: Mr | D895: John | E895: Butcher
A896: Id895 | B896: Traiser, Mr. Miles J. | C896: Mr | D896: Miles J | E896: Traiser
A897: Id896 | B897: Mudy-Mader, Ms. Justyna I. | C897: Ms | D897: Justyna I | E897: Mudy-Mader
A898: Id897 | B898: Rogers, Ms. Lucille | C898: Ms | D898: Lucille | E898: Rogers
A899: Id898 | B899: Woo, Ms. April | C899: Ms | D899: April | E899: Woo
A900: Id899 | B900: Walsh, Mr. Robert | C900: Mr | D900: Robert | E900: Walsh
A901: Id900 | B901: White, Mrs. Alyssa | C901: Mrs | D901: Alyssa | E901: White
A902: Id901 | B902: Sheppard, Ms. Jessica E. | C902: Ms | D902: Jessica E | E902: Sheppard
A903: Id902 | B903: Doran, Mr. Patrick J. | C903: Mr | D903: Patrick J | E903: Doran
A904: Id903 | B904: Labrosse, Ms. Emilie | C904: Ms | D904: Emilie | E904: Labrosse
A905: Id904 | B905: Thomas, Ms. Caitlin B. | C905: Ms | D905: Caitlin B | E905: Thomas
... A1062: Id1061 | B1062: Dockemeyer, Mr. Kevin J | C1062: Mr | D1062: Kevin J | E1062: Dockemeyer
A1063: Id1062 | B1063: Steele, Mr. William H. Iii | C1063: Mr | D1063: William H | E1063: Steele | H1063: Iii
A1064: Id1063 | B1064: Harel, Mr. Gal | C1064: Mr | D1064: Gal | E1064: Harel
A1065: Id1064 | B1065: Aguila, Mr. Anton | C1065: Mr | D1065: Anton | E1065: Aguila
A1066: Id1065 | B1066: Vallejo Sarmiento, Ms. Yazmin | C1066: Ms | D1066: Yazmin | E1066: Vallejo Sarmiento
A1067: Id1066 | B1067: Beisheim, Mr. Florian | C1067: Mr | D1067: Florian | E1067: Beisheim
A1068: Id1067 | B1068: Lenhoff, Ms. Karen L | C1068: Ms | D1068: Karen L | E1068: Lenhoff
A1069: Id1068 | B1069: Wehrwein, Mr. Scott | C1069: Mr | D1069: Scott | E1069: Wehrwein
A1070: Id1069 | B1070: Wallace, Ms. Claire | C1070: Ms | D1070: Claire | E1070: Wallace
A1071: Id1070 | B1071: Markowitz, Ms. Lynn M. | C1071: Ms | D1071: Lynn M | E1071: Markowitz
A1072: Id1071 | B1072: Vos, Ms. Sharon | C1072: Ms | D1072: Sharon | E1072: Vos
A1073: Id1072 | B1073: Mcleod, Mrs. Candice | C1073: Mrs | D1073: Candice | E1073: Mcleod
A1074: Id1073 | B1074: Balcom, Ms. Jennifer D | C1074: Ms | D1074: Jennifer D | E1074: Balcom
A1075: Id1074 | B1075: Dirth, Mr. Eric | C1075: Mr | D1075: Eric | E1075: Dirth
... A1295: Id1294 | B1295: Tadich, Ms. Katarina D | C1295: Ms | D1295: Katarina D | E1295: Tadich
A1296: Id1295 | B1296: Christenson, Mr. B.J. | C1296: Mr | D1296: B | E1296: Christenson | H1296: J
A1297: Id1296 | B1297: Shell, Ms. Alison | C1297: Ms | D1297: Alison | E1297: Shell
A1298: Id1297 | B1298: Rao, Mr. Neil K. | C1298: Mr | D1298: Neil K | E1298: Rao
...

Sheet Midical Examination
A1: Customer ID | B1: BMI | C1: HBA1C | D1: Heart Issues | E1: Any Transplants | F1: Cancer history | G1: NumberOfMajorSurgeries | H1: smoker | I1: Weight Status | U1: Encoding | V1: Mode
A2: Id1 | B2: 47.41 | C2: 7.47 | D2: No | E2: No | F2: No | G2: 0 | H2: yes | I2: =IF(B2<18.5,"Underweight",IF(B2<25,"Normal Weight",IF(B2<30,"Overweight","Obesity"))) -> Obesity | U2: {=MATCH(H2:H2336,H2:H2336,0)} -> 1 | V2: =MODE(_xlfn.ANCHORARRAY(U2)) -> 180
A3: Id2 | B3: 30.36 | C3: 5.77 | D3: No | E3: No | F3: No | G3: 0 | H3: yes | I3: =IF(B3<18.5,"Underweight",IF(B3<25,"Normal Weight",IF(B3<30,"Overweight","Obesity"))) -> Obesity | U3: 1 | V3: Index
A4: Id3 | B4: 34.485 | C4: 11.87 | D4: yes | E4: No | F4: No | G4: 2 | H4: yes | I4: =IF(B4<18.5,"Underweight",IF(B4<25,"Normal Weight",IF(B4<30,"Overweight","Obesity"))) -> Obesity | U4: 1 | V4: {=INDEX(H2:H2336,V2)} -> No
A5: Id4 | B5: 38.095 | C5: 6.05 | D5: No | E5: No | F5: No | G5: 0 | H5: yes | I5: =IF(B5<18.5,"Underweight",IF(B5<25,"Normal Weight",IF(B5<30,"Overweight","Obesity"))) -> Obesity | U5: 1
A6: Id5 | B6: 35.53 | C6: 5.45 | D6: No | E6: No | F6: No | G6: 0 | H6: yes | I6: =IF(B6<18.5,"Underweight",IF(B6<25,"Normal Weight",IF(B6<30,"Overweight","Obesity"))) -> Obesity | U6: 1
A7: Id6 | B7: 32.8 | C7: 6.59 | D7: No | E7: No | F7: No | G7: 0 | H7: yes | I7: =IF(B7<18.5,"Underweight",IF(B7<25,"Normal Weight",IF(B7<30,"Overweight","Obesity"))) -> Obesity | U7: 1
A8: Id7 | B8: 36.4 | C8: 6.07 | D8: No | E8: No | F8: No | G8: 0 | H8: yes | I8: =IF(B8<18.5,"Underweight",IF(B8<25,"Normal Weight",IF(B8<30,"Overweight","Obesity"))) -> Obesity | U8: 1
A9: Id8 | B9: 36.96 | C9: 7.93 | D9: No | E9: No | F9: No | G9: 3 | H9: yes | I9: =IF(B9<18.5,"Underweight",IF(B9<25,"Normal Weight",IF(B9<30,"Overweight","Obesity"))) -> Obesity | U9: 1
A10: Id9 | B10: 41.14 | C10: 9.58 | D10: yes | E10: No | F10: Yes | G10: 1 | H10: yes | I10: =IF(B10<18.5,"Underweight",IF(B10<25,"Normal Weight",IF(B10<30,"Overweight","Obesity"))) -> Obesity | U10: 1
A11: Id10 | B11: 38.06 | C11: 10.79 | D11: No | E11: No | F11: No | G11: 0 | H11: yes | I11: =IF(B11<18.5,"Underweight",IF(B11<25,"Normal Weight",IF(B11<30,"Overweight","Obesity"))) -> Obesity | U11: 1
A12: Id11 | B12: 37.7 | C12: 5.96 | D12: yes | E12: No | F12: No | G12: 2 | H12: yes | I12: =IF(B12<18.5,"Underweight",IF(B12<25,"Normal Weight",IF(B12<30,"Overweight","Obesity"))) -> Obesity | U12: 1
A13: Id12 | B13: 42.13 | C13: 11.9 | D13: No | E13: No | F13: No | G13: 0 | H13: yes | I13: =IF(B13<18.5,"Underweight",IF(B13<25,"Normal Weight",IF(B13<30,"Overweight","Obesity"))) -> Obesity | U13: 1
A14: Id13 | B14: 40.92 | C14: 8.41 | D14: No | E14: No | F14: No | G14: 0 | H14: yes | I14: =IF(B14<18.5,"Underweight",IF(B14<25,"Normal Weight",IF(B14<30,"Overweight","Obesity"))) -> Obesity | U14: 1
A15: Id14 | B15: 40.565 | C15: 7.02 | D15: No | E15: No | F15: No | G15: 0 | H15: yes | I15: =IF(B15<18.5,"Underweight",IF(B15<25,"Normal Weight",IF(B15<30,"Overweight","Obesity"))) -> Obesity | U15: 1
A16: Id15 | B16: 36.385 | C16: 7.59 | D16: yes | E16: No | F16: No | G16: 2 | H16: yes | I16: =IF(B16<18.5,"Underweight",IF(B16<25,"Normal Weight",IF(B16<30,"Overweight","Obesity"))) -> Obesity | U16: 1
... A2336: Id2335 | B2336: 17.58 | C2336: 4.51 | D2336: No | E2336: No | F2336: No | G2336: 1 | H2336: No | I2336: =IF(B2336<18.5,"Underweight",IF(B2336<25,"Normal Weight",IF(B2336<30,"Overweight","Obesity"))) -> Underweight | U2336: 180
B2337: =AVERAGE(B2:B2336) -> 30.972649 | C2337: =AVERAGE(C2:C2336) -> 6.5789979 | G2337: =AVERAGE(G2:G2336) -> 0.67623126

Sheet Hospitalisation Details
A1: Customer ID | B1: Year | C1: Month | D1: Date | E1: Children | F1: Charges | G1: Hospital Tier | H1: City Tier | I1: State ID | J1: Average Year | K1: Cleaned Year | L1: Date of Birth | M1: Age | V1: Encoding | W1: Mode
A2: Id2335 | B2: 1992 | C2: Jul | D2: 9 | E2: 0 | F2: 563.84 | G2: tier - 2 | H2: tier - 3 | I2: R1013 | J2: =ROUND(AVERAGEIF($B$2:$B$2339,"<>Unknown"),0) -> 1983 | K2: =IF(B2="Unknown",$J$2,B2) -> 1992 | L2: =DATE(K2, MONTH(1 &C2),D2) -> 33794 | M2: =DATEDIF(L2, DATE(2023,6,8),"y") -> 30 | V2: {=MATCH(H2:H2339,H2:H2339,0)} -> 1 | W2: =MODE(_xlfn.ANCHORARRAY(V2)) -> 9
A3: Id2334 | B3: 1992 | C3: Nov | D3: 30 | E3: 0 | F3: 570.62 | G3: tier - 2 | H3: tier - 1 | I3: R1013 | J3: =ROUND(AVERAGEIF($B$2:$B$2339,"<>Unknown"),0) -> 1983 | K3: =IF(B3="Unknown",$J$2,B3) -> 1992 | L3: =DATE(K3, MONTH(1 &C3),D3) -> 33938 | M3: =DATEDIF(L3, DATE(2023,6,8),"y") -> 30 | V3: 2 | W3: Index
A4: Id2333 | B4: 1993 | C4: Jun | D4: 30 | E4: 0 | F4: 600 | G4: tier - 2 | H4: tier - 1 | I4: R1013 | J4: =ROUND(AVERAGEIF($B$2:$B$2339,"<>Unknown"),0) -> 1983 | K4: =IF(B4="Unknown",$J$2,B4) -> 1993 | L4: =DATE(K4, MONTH(1 &C4),D4) -> 34150 | M4: =DATEDIF(L4, DATE(2023,6,8),"y") -> 29 | V4: 2 | W4: {=INDEX(H2:H2339,W2)} -> tier - 2
A5: Id2332 | B5: 1992 | C5: Sep | D5: 13 | E5: 0 | F5: 604.54 | G5: tier - 3 | H5: tier - 3 | I5: R1013 | J5: =ROUND(AVERAGEIF($B$2:$B$2339,"<>Unknown"),0) -> 1983 | K5: =IF(B5="Unknown",$J$2,B5) -> 1992 | L5: =DATE(K5, MONTH(1 &C5),D5) -> 33860 | M5: =DATEDIF(L5, DATE(2023,6,8),"y") -> 30 | V5: 1
A6: Id2331 | B6: 1998 | C6: Jul | D6: 27 | E6: 0 | F6: 637.26 | G6: tier - 3 | H6: tier - 3 | I6: R1013 | J6: =ROUND(AVERAGEIF($B$2:$B$2339,"<>Unknown"),0) -> 1983 | K6: =IF(B6="Unknown",$J$2,B6) -> 1998 | L6: =DATE(K6, MONTH(1 &C6),D6) -> 36003 | M6: =DATEDIF(L6, DATE(2023,6,8),"y") -> 24 | V6: 1
A7: Id2330 | B7: 2001 | C7: Nov | D7: 20 | E7: 0 | F7: 646.14 | G7: tier - 3 | H7: tier - 3 | I7: R1012 | J7: =ROUND(AVERAGEIF($B$2:$B$2339,"<>Unknown"),0) -> 1983 | K7: =IF(B7="Unknown",$J$2,B7) -> 2001 | L7: =DATE(K7, MONTH(1 &C7),D7) -> 37215 | M7: =DATEDIF(L7, DATE(2023,6,8),"y") -> 21 | V7: 1
A8: Id2329 | B8: 1993 | C8: Jun | D8: 1 | E8: 0 | F8: 650 | G8: tier - 3 | H8: tier - 3 | I8: R1013 | J8: =ROUND(AVERAGEIF($B$2:$B$2339,"<>Unknown"),0) -> 1983 | K8: =IF(B8="Unknown",$J$2,B8) -> 1993 | L8: =DATE(K8, MONTH(1 &C8),D8) -> 34121 | M8: =DATEDIF(L8, DATE(2023,6,8),"y") -> 30 | V8: 1
A9: Id2328 | B9: 1995 | C9: Jul | D9: 4 | E9: 0 | F9: 650 | G9: tier - 3 | H9: tier - 3 | I9: R1013 | J9: =ROUND(AVERAGEIF($B$2:$B$2339,"<>Unknown"),0) -> 1983 | K9: =IF(B9="Unknown",$J$2,B9) -> 1995 | L9: =DATE(K9, MONTH(1 &C9),D9) -> 34884 | M9: =DATEDIF(L9, DATE(2023,6,8),"y") -> 27 | V9: 1
A10: Id2327 | B10: 2002 | C10: Nov | D10: 29 | E10: 0 | F10: 668 | G10: tier - 3 | H10: tier - 2 | I10: R1012 | J10: =ROUND(AVERAGEIF($B$2:$B$2339,"<>Unknown"),0) -> 1983 | K10: =IF(B10="Unknown",$J$2,B10) -> 2002 | L10: =DATE(K10, MONTH(1 &C10),D10) -> 37589 | M10: =DATEDIF(L10, DATE(2023,6,8),"y") -> 20 | V10: 9
A11: Id2326 | B11: 1997 | C11: Nov | D11: 9 | E11: 0 | F11: 670 | G11: tier - 3 | H11: tier - 3 | I11: R1013 | J11: =ROUND(AVERAGEIF($B$2:$B$2339,"<>Unknown"),0) -> 1983 | K11: =IF(B11="Unknown",$J$2,B11) -> 1997 | L11: =DATE(K11, MONTH(1 &C11),D11) -> 35743 | M11: =DATEDIF(L11, DATE(2023,6,8),"y") -> 25 | V11: 1
A12: Id2325 | B12: 2001 | C12: Sep | D12: 12 | E12: 0 | F12: 687.54 | G12: tier - 3 | H12: tier - 2 | I12: R1013 | J12: =ROUND(AVERAGEIF($B$2:$B$2339,"<>Unknown"),0) -> 1983 | K12: =IF(B12="Unknown",$J$2,B12) -> 2001 | L12: =DATE(K12, MONTH(1 &C12),D12) -> 37146 | M12: =DATEDIF(L12, DATE(2023,6,8),"y") -> 21 | V12: 9
A13: Id2324 | B13: 1999 | C13: Dec | D13: 26 | E13: 0 | F13: 700 | G13: tier - 2 | H13: tier - 3 | I13: R1013 | J13: =ROUND(AVERAGEIF($B$2:$B$2339,"<>Unknown"),0) -> 1983 | K13: =IF(B13="Unknown",$J$2,B13) -> 1999 | L13: =DATE(K13, MONTH(1 &C13),D13) -> 36520 | M13: =DATEDIF(L13, DATE(2023,6,8),"y") -> 23 | V13: 1
A14: Id2323 | B14: 1999 | C14: Dec | D14: 14 | E14: 0 | F14: 722.99 | G14: tier - 3 | H14: tier - 1 | I14: R1013 | J14: =ROUND(AVERAGEIF($B$2:$B$2339,"<>Unknown"),0) -> 1983 | K14: =IF(B14="Unknown",$J$2,B14) -> 1999 | L14: =DATE(K14, MONTH(1 &C14),D14) -> 36508 | M14: =DATEDIF(L14, DATE(2023,6,8),"y") -> 23 | V14: 2
A15: Id2322 | B15: 2002 | C15: Sep | D15: 19 | E15: 0 | F15: 750 | G15: tier - 3 | H15: tier - 1 | I15: R1012 | J15: =ROUND(AVERAGEIF($B$2:$B$2339,"<>Unknown"),0) -> 1983 | K15: =IF(B15="Unknown",$J$2,B15) -> 2002 | L15: =DATE(K15, MONTH(1 &C15),D15) -> 37518 | M15: =DATEDIF(L15, DATE(2023,6,8),"y") -> 20 | V15: 2
A16: Id2321 | B16: 1993 | C16: Aug | D16: 9 | E16: 0 | F16: 760 | G16: tier - 3 | H16: tier - 1 | I16: R1013 | J16: =ROUND(AVERAGEIF($B$2:$B$2339,"<>Unknown"),0) -> 1983 | K16: =IF(B16="Unknown",$J$2,B16) -> 1993 | L16: =DATE(K16, MONTH(1 &C16),D16) -> 34190 | M16: =DATEDIF(L16, DATE(2023,6,8),"y") -> 29 | V16: 2
... A1048: Id1290 | B1048: 1977 | C1048: Jul | D1048: 26 | E1048: 2 | F1048: 8527.53 | G1048: tier - 2 | H1048: tier - 2 | I1048: R1013 | J1048: =ROUND(AVERAGEIF($B$2:$B$2339,"<>Unknown"),0) -> 1983 | K1048: =IF(B1048="Unknown",$J$2,B1048) -> 1977 | L1048: =DATE(K1048, MONTH(1 &C1048),D1048) -> 28332 | M1048: =DATEDIF(L1048, DATE(2023,6,8),"y") -> 45 | V1048: 9
A1049: Id1289 | B1049: Unknown | C1049: Jul | D1049: 24 | E1049: 0 | F1049: 8534.67 | G1049: tier - 2 | H1049: tier - 3 | I1049: R1024 | J1049: =ROUND(AVERAGEIF($B$2:$B$2339,"<>Unknown"),0) -> 1983 | K1049: =IF(B1049="Unknown",$J$2,B1049) -> 1983 | L1049: =DATE(K1049, MONTH(1 &C1049),D1049) -> 30521 | M1049: =DATEDIF(L1049, DATE(2023,6,8),"y") -> 39 | V1049: 1
A1050: Id1288 | B1050: 1981 | C1050: Dec | D1050: 27 | E1050: 3 | F1050: 8538.29 | G1050: tier - 2 | H1050: tier - 3 | I1050: R1024 | J1050: =ROUND(AVERAGEIF($B$2:$B$2339,"<>Unknown"),0) -> 1983 | K1050: =IF(B1050="Unknown",$J$2,B1050) -> 1981 | L1050: =DATE(K1050, MONTH(1 &C1050),D1050) -> 29947 | M1050: =DATEDIF(L1050, DATE(2023,6,8),"y") -> 41 | V1050: 1
A1051: Id1287 | B1051: 1975 | C1051: Nov | D1051: 6 | E1051: 1 | F1051: 8539.67 | G1051: tier - 2 | H1051: tier - 3 | I1051: R1011 | J1051: =ROUND(AVERAGEIF($B$2:$B$2339,"<>Unknown"),0) -> 1983 | K1051: =IF(B1051="Unknown",$J$2,B1051) -> 1975 | L1051: =DATE(K1051, MONTH(1 &C1051),D1051) -> 27704 | M1051: =DATEDIF(L1051, DATE(2023,6,8),"y") -> 47 | V1051: 1
A1052: Id1286 | B1052: Unknown | C1052: Dec | D1052: 12 | E1052: 1 | F1052: 8547.69 | G1052: tier - 2 | H1052: tier - 1 | I1052: R1013 | J1052: =ROUND(AVERAGEIF($B$2:$B$2339,"<>Unknown"),0) -> 1983 | K1052: =IF(B1052="Unknown",$J$2,B1052) -> 1983 | L1052: =DATE(K1052, MONTH(1 &C1052),D1052) -> 30662 | M1052: =DATEDIF(L1052, DATE(2023,6,8),"y") -> 39 | V1052: 2
A1053: Id1285 | B1053: 1975 | C1053: Aug | D1053: 6 | E1053: 1 | F1053: 8551.35 | G1053: tier - 2 | H1053: tier - 2 | I1053: R1011 | J1053: =ROUND(AVERAGEIF($B$2:$B$2339,"<>Unknown"),0) -> 1983 | K1053: =IF(B1053="Unknown",$J$2,B1053) -> 1975 | L1053: =DATE(K1053, MONTH(1 &C1053),D1053) -> 27612 | M1053: =DATEDIF(L1053, DATE(2023,6,8),"y") -> 47 | V1053: 9
A1054: Id1284 | B1054: 1975 | C1054: Aug | D1054: 21 | E1054: 1 | F1054: 8556.91 | G1054: tier - 2 | H1054: tier - 1 | I1054: R1011 | J1054: =ROUND(AVERAGEIF($B$2:$B$2339,"<>Unknown"),0) -> 1983 | K1054: =IF(B1054="Unknown",$J$2,B1054) -> 1975 | L1054: =DATE(K1054, MONTH(1 &C1054),D1054) -> 27627 | M1054: =DATEDIF(L1054, DATE(2023,6,8),"y") -> 47 | V1054: 2
A1055: Id1283 | B1055: 1988 | C1055: Sep | D1055: 21 | E1055: 3 | F1055: 8567.25 | G1055: tier - 2 | H1055: tier - 1 | I1055: R1012 | J1055: =ROUND(AVERAGEIF($B$2:$B$2339,"<>Unknown"),0) -> 1983 | K1055: =IF(B1055="Unknown",$J$2,B1055) -> 1988 | L1055: =DATE(K1055, MONTH(1 &C1055),D1055) -> 32407 | M1055: =DATEDIF(L1055, DATE(2023,6,8),"y") -> 34 | V1055: 2
A1056: Id1282 | B1056: 1975 | C1056: Sep | D1056: 26 | E1056: 1 | F1056: 8569.86 | G1056: tier - 2 | H1056: tier - 3 | I1056: R1013 | J1056: =ROUND(AVERAGEIF($B$2:$B$2339,"<>Unknown"),0) -> 1983 | K1056: =IF(B1056="Unknown",$J$2,B1056) -> 1975 | L1056: =DATE(K1056, MONTH(1 &C1056),D1056) -> 27663 | M1056: =DATEDIF(L1056, DATE(2023,6,8),"y") -> 47 | V1056: 1
A1057: Id1281 | B1057: 1982 | C1057: Dec | D1057: 6 | E1057: 3 | F1057: 8572.04 | G1057: tier - 2 | H1057: tier - 2 | I1057: R1021 | J1057: =ROUND(AVERAGEIF($B$2:$B$2339,"<>Unknown"),0) -> 1983 | K1057: =IF(B1057="Unknown",$J$2,B1057) -> 1982 | L1057: =DATE(K1057, MONTH(1 &C1057),D1057) -> 30291 | M1057: =DATEDIF(L1057, DATE(2023,6,8),"y") -> 40 | V1057: 9
A1058: Id1280 | B1058: 1987 | C1058: Nov | D1058: 11 | E1058: 3 | F1058: 8573.3 | G1058: tier - 2 | H1058: tier - 2 | I1058: R1021 | J1058: =ROUND(AVERAGEIF($B$2:$B$2339,"<>Unknown"),0) -> 1983 | K1058: =IF(B1058="Unknown",$J$2,B1058) -> 1987 | L1058: =DATE(K1058, MONTH(1 &C1058),D1058) -> 32092 | M1058: =DATEDIF(L1058, DATE(2023,6,8),"y") -> 35 | V1058: 9
A1059: Id1279 | B1059: 1983 | C1059: Dec | D1059: 30 | E1059: 5 | F1059: 8582.3 | G1059: tier - 2 | H1059: tier - 1 | I1059: R1013 | J1059: =ROUND(AVERAGEIF($B$2:$B$2339,"<>Unknown"),0) -> 1983 | K1059: =IF(B1059="Unknown",$J$2,B1059) -> 1983 | L1059: =DATE(K1059, MONTH(1 &C1059),D1059) -> 30680 | M1059: =DATEDIF(L1059, DATE(2023,6,8),"y") -> 39 | V1059: 2
A1060: Id1278 | B1060: 1983 | C1060: Jul | D1060: 25 | E1060: 5 | F1060: 8596.83 | G1060: tier - 2 | H1060: tier - 3 | I1060: R1013 | J1060: =ROUND(AVERAGEIF($B$2:$B$2339,"<>Unknown"),0) -> 1983 | K1060: =IF(B1060="Unknown",$J$2,B1060) -> 1983 | L1060: =DATE(K1060, MONTH(1 &C1060),D1060) -> 30522 | M1060: =DATEDIF(L1060, DATE(2023,6,8),"y") -> 39 | V1060: 1
A1061: Id1277 | B1061: 1973 | C1061: Jul | D1061: 11 | E1061: 0 | F1061: 8601.33 | G1061: tier - 2 | H1061: tier - 1 | I1061: R1013 | J1061: =ROUND(AVERAGEIF($B$2:$B$2339,"<>Unknown"),0) -> 1983 | K1061: =IF(B1061="Unknown",$J$2,B1061) -> 1973 | L1061: =DATE(K1061, MONTH(1 &C1061),D1061) -> 26856 | M1061: =DATEDIF(L1061, DATE(2023,6,8),"y") -> 49 | V1061: 2
A1062: Id1276 | B1062: 1977 | C1062: Sep | D1062: 24 | E1062: 2 | F1062: 8603.82 | G1062: tier - 2 | H1062: tier - 1 | I1062: R1019 | J1062: =ROUND(AVERAGEIF($B$2:$B$2339,"<>Unknown"),0) -> 1983 | K1062: =IF(B1062="Unknown",$J$2,B1062) -> 1977 | L1062: =DATE(K1062, MONTH(1 &C1062),D1062) -> 28392 | M1062: =DATEDIF(L1062, DATE(2023,6,8),"y") -> 45 | V1062: 2
A1063: Id1275 | B1063: 1977 | C1063: Nov | D1063: 12 | E1063: 2 | F1063: 8604.48 | G1063: tier - 3 | H1063: tier - 2 | I1063: R1016 | J1063: =ROUND(AVERAGEIF($B$2:$B$2339,"<>Unknown"),0) -> 1983 | K1063: =IF(B1063="Unknown",$J$2,B1063) -> 1977 | L1063: =DATE(K1063, MONTH(1 &C1063),D1063) -> 28441 | M1063: =DATEDIF(L1063, DATE(2023,6,8),"y") -> 45 | V1063: 9
A1064: Id1274 | B1064: 1977 | C1064: Oct | D1064: 15 | E1064: 3 | F1064: 8605.36 | G1064: tier - 2 | H1064: tier - 2 | I1064: R1013 | J1064: =ROUND(AVERAGEIF($B$2:$B$2339,"<>Unknown"),0) -> 1983 | K1064: =IF(B1064="Unknown",$J$2,B1064) -> 1977 | L1064: =DATE(K1064, MONTH(1 &C1064),D1064) -> 28413 | M1064: =DATEDIF(L1064, DATE(2023,6,8),"y") -> 45 | V1064: 9
... A2339: Id1 | B2339: 1968 | C2339: Oct | D2339: 12 | E2339: 0 | F2339: 63770.43 | G2339: tier - 1 | H2339: tier - 3 | I2339: R1013 | J2339: =ROUND(AVERAGEIF($B$2:$B$2339,"<>Unknown"),0) -> 1983 | K2339: =IF(B2339="Unknown",$J$2,B2339) -> 1968 | L2339: =DATE(K2339, MONTH(1 &C2339),D2339) -> 25123 | M2339: =DATEDIF(L2339, DATE(2023,6,8),"y") -> 54 | V2339: 1
A2340: =COUNTA(A2:A2339) -> 2338 | M2340: =AVERAGE(M2:M2339) -> 39.208725

Sheet Healthcare
A1: Customer ID | B1: First Name | C1: BMI | D1: HBA1C | E1: Heart Issues | F1: Any Transplants | G1: Cancer History | H1: Number Of Major Surgeries | I1: smoker | J1: Weight Status | K1: Diabetes Status | L1: Date of Birth | M1: charges | N1: Hospital tier | O1: City tier | P1: State ID | Q1: Age | R1: Age Group
A2: Id1 | B2: =_xlfn.XLOOKUP(A2,'Customer Names'!$A$2:$A$2336,'Customer Names'!$D$2:$D$2336) -> Kelly | C2: =_xlfn.XLOOKUP(A2,'Midical Examination'!$A$2:$A$2336,'Midical Examination'!$B$2:$B$2336) -> 47.41 | D2: =_xlfn.XLOOKUP(A2,'Midical Examination'!$A$2:$A$2336,'Midical Examination'!$C$2:$C$2336) -> 7.47 | E2: =_xlfn.XLOOKUP(A2,'Midical Examination'!$A$2:$A$2336,'Midical Examination'!$D$2:$D$2336) -> No | F2: =_xlfn.XLOOKUP(A2,'Midical Examination'!$A$2:$A$2336,'Midical Examination'!$E$2:$E$2336) -> No | G2: =_xlfn.XLOOKUP(A2,'Midical Examination'!$A$2:$A$2336,'Midical Examination'!$F$2:$F$2336) -> No | H2: =_xlfn.XLOOKUP(A2,'Midical Examination'!$A$2:$A$2336,'Midical Examination'!$G$2:$G$2336) -> 0 | I2: =_xlfn.XLOOKUP(A2,'Midical Examination'!$A$2:$A$2336,'Midical Examination'!$H$2:$H$2336) -> yes | J2: =_xlfn.XLOOKUP(A2,'Midical Examination'!$A$2:$A$2336,'Midical Examination'!$I$2:$I$2336) -> Obesity | K2: =IF(D2<5.7, "Normal", IF(D2<6.5,"Pre-Diabetic", "Diabetic")) -> Diabetic | L2: =_xlfn.XLOOKUP(A2,'Hospitalisation Details'!$A$2:$A$2339,'Hospitalisation Details'!$L$2:$L$2339) -> 25123 | M2: =_xlfn.XLOOKUP(A2,'Hospitalisation Details'!$A$2:$A$2339,'Hospitalisation Details'!$F$2:$F$2339) -> 63770.43 | N2: =_xlfn.XLOOKUP(A2,'Hospitalisation Details'!$A$2:$A$2339,'Hospitalisation Details'!$G$2:$G$2339) -> tier - 1 | O2: =_xlfn.XLOOKUP(A2,'Hospitalisation Details'!$A$2:$A$2339,'Hospitalisation Details'!$H$2:$H$2339) -> tier - 3 | P2: =_xlfn.XLOOKUP(A2,'Hospitalisation Details'!$A$2:$A$2339,'Hospitalisation Details'!$I$2:$I$2339) -> R1013 | Q2: =_xlfn.XLOOKUP(A2,'Hospitalisation Details'!$A$2:$A$2339,'Hospitalisation Details'!$M$2:$M$2339) -> 54 | R2: =IF(Q2<20, "Young",IF(Q2<40,"Adult",IF(Q2<60, "Middle Aged", "Senior"))) -> Middle Aged
A3: Id2 | B3: =_xlfn.XLOOKUP(A3,'Customer Names'!$A$2:$A$2336,'Customer Names'!$D$2:$D$2336) -> Matthew D | C3: =_xlfn.XLOOKUP(A3,'Midical Examination'!$A$2:$A$2336,'Midical Examination'!$B$2:$B$2336) -> 30.36 | D3: =_xlfn.XLOOKUP(A3,'Midical Examination'!$A$2:$A$2336,'Midical Examination'!$C$2:$C$2336) -> 5.77 | E3: =_xlfn.XLOOKUP(A3,'Midical Examination'!$A$2:$A$2336,'Midical Examination'!$D$2:$D$2336) -> No | F3: =_xlfn.XLOOKUP(A3,'Midical Examination'!$A$2:$A$2336,'Midical Examination'!$E$2:$E$2336) -> No | G3: =_xlfn.XLOOKUP(A3,'Midical Examination'!$A$2:$A$2336,'Midical Examination'!$F$2:$F$2336) -> No | H3: =_xlfn.XLOOKUP(A3,'Midical Examination'!$A$2:$A$2336,'Midical Examination'!$G$2:$G$2336) -> 0 | I3: =_xlfn.XLOOKUP(A3,'Midical Examination'!$A$2:$A$2336,'Midical Examination'!$H$2:$H$2336) -> yes | J3: =_xlfn.XLOOKUP(A3,'Midical Examination'!$A$2:$A$2336,'Midical Examination'!$I$2:$I$2336) -> Obesity | K3: =IF(D3<5.7, "Normal", IF(D3<6.5,"Pre-Diabetic", "Diabetic")) -> Pre-Diabetic | L3: =_xlfn.XLOOKUP(A3,'Hospitalisation Details'!$A$2:$A$2339,'Hospitalisation Details'!$L$2:$L$2339) -> 28284 | M3: =_xlfn.XLOOKUP(A3,'Hospitalisation Details'!$A$2:$A$2339,'Hospitalisation Details'!$F$2:$F$2339) -> 62592.87 | N3: =_xlfn.XLOOKUP(A3,'Hospitalisation Details'!$A$2:$A$2339,'Hospitalisation Details'!$G$2:$G$2339) -> tier - 2 | O3: =_xlfn.XLOOKUP(A3,'Hospitalisation Details'!$A$2:$A$2339,'Hospitalisation Details'!$H$2:$H$2339) -> tier - 3 | P3: =_xlfn.XLOOKUP(A3,'Hospitalisation Details'!$A$2:$A$2339,'Hospitalisation Details'!$I$2:$I$2339) -> R1013 | Q3: =_xlfn.XLOOKUP(A3,'Hospitalisation Details'!$A$2:$A$2339,'Hospitalisation Details'!$M$2:$M$2339) -> 46 | R3: =IF(Q3<20, "Young",IF(Q3<40,"Adult",IF(Q3<60, "Middle Aged", "Senior"))) -> Middle Aged | T3: Metric | X3: Value
A4: Id3 | B4: =_xlfn.XLOOKUP(A4,'Customer Names'!$A$2:$A$2336,'Customer Names'!$D$2:$D$2336) -> Phil | C4: =_xlfn.XLOOKUP(A4,'Midical Examination'!$A$2:$A$2336,'Midical Examination'!$B$2:$B$2336) -> 34.485 | D4: =_xlfn.XLOOKUP(A4,'Midical Examination'!$A$2:$A$2336,'Midical Examination'!$C$2:$C$2336) -> 11.87 | E4: =_xlfn.XLOOKUP(A4,'Midical Examination'!$A$2:$A$2336,'Midical Examination'!$D$2:$D$2336) -> yes | F4: =_xlfn.XLOOKUP(A4,'Midical Examination'!$A$2:$A$2336,'Midical Examination'!$E$2:$E$2336) -> No | G4: =_xlfn.XLOOKUP(A4,'Midical Examination'!$A$2:$A$2336,'Midical Examination'!$F$2:$F$2336) -> No | H4: =_xlfn.XLOOKUP(A4,'Midical Examination'!$A$2:$A$2336,'Midical Examination'!$G$2:$G$2336) -> 2 | I4: =_xlfn.XLOOKUP(A4,'Midical Examination'!$A$2:$A$2336,'Midical Examination'!$H$2:$H$2336) -> yes | J4: =_xlfn.XLOOKUP(A4,'Midical Examination'!$A$2:$A$2336,'Midical Examination'!$I$2:$I$2336) -> Obesity | K4: =IF(D4<5.7, "Normal", IF(D4<6.5,"Pre-Diabetic", "Diabetic")) -> Diabetic | L4: =_xlfn.XLOOKUP(A4,'Hospitalisation Details'!$A$2:$A$2339,'Hospitalisation Details'!$L$2:$L$2339) -> 25822 | M4: =_xlfn.XLOOKUP(A4,'Hospitalisation Details'!$A$2:$A$2339,'Hospitalisation Details'!$F$2:$F$2339) -> 60021.4 | N4: =_xlfn.XLOOKUP(A4,'Hospitalisation Details'!$A$2:$A$2339,'Hospitalisation Details'!$G$2:$G$2339) -> tier - 1 | O4: =_xlfn.XLOOKUP(A4,'Hospitalisation Details'!$A$2:$A$2339,'Hospitalisation Details'!$H$2:$H$2339) -> tier - 1 | P4: =_xlfn.XLOOKUP(A4,'Hospitalisation Details'!$A$2:$A$2339,'Hospitalisation Details'!$I$2:$I$2339) -> R1012 | Q4: =_xlfn.XLOOKUP(A4,'Hospitalisation Details'!$A$2:$A$2339,'Hospitalisation Details'!$M$2:$M$2339) -> 52 | R4: =IF(Q4<20, "Young",IF(Q4<40,"Adult",IF(Q4<60, "Middle Aged", "Senior"))) -> Middle Aged | T4: Average costs and medical metrics | X4: 31592359
A5: Id4 | B5: =_xlfn.XLOOKUP(A5,'Customer Names'!$A$2:$A$2336,'Customer Names'!$D$2:$D$2336) -> Kelsey | C5: =_xlfn.XLOOKUP(A5,'Midical Examination'!$A$2:$A$2336,'Midical Examination'!$B$2:$B$2336) -> 38.095 | D5: =_xlfn.XLOOKUP(A5,'Midical Examination'!$A$2:$A$2336,'Midical Examination'!$C$2:$C$2336) -> 6.05 | E5: =_xlfn.XLOOKUP(A5,'Midical Examination'!$A$2:$A$2336,'Midical Examination'!$D$2:$D$2336) -> No | F5: =_xlfn.XLOOKUP(A5,'Midical Examination'!$A$2:$A$2336,'Midical Examination'!$E$2:$E$2336) -> No | G5: =_xlfn.XLOOKUP(A5,'Midical Examination'!$A$2:$A$2336,'Midical Examination'!$F$2:$F$2336) -> No | H5: =_xlfn.XLOOKUP(A5,'Midical Examination'!$A$2:$A$2336,'Midical Examination'!$G$2:$G$2336) -> 0 | I5: =_xlfn.XLOOKUP(A5,'Midical Examination'!$A$2:$A$2336,'Midical Examination'!$H$2:$H$2336) -> yes | J5: =_xlfn.XLOOKUP(A5,'Midical Examination'!$A$2:$A$2336,'Midical Examination'!$I$2:$I$2336) -> Obesity | K5: =IF(D5<5.7, "Normal", IF(D5<6.5,"Pre-Diabetic", "Diabetic")) -> Pre-Diabetic | L5: =_xlfn.XLOOKUP(A5,'Hospitalisation Details'!$A$2:$A$2339,'Hospitalisation Details'!$L$2:$L$2339) -> 33395 | M5: =_xlfn.XLOOKUP(A5,'Hospitalisation Details'!$A$2:$A$2339,'Hospitalisation Details'!$F$2:$F$2339) -> 58571.07 | N5: =_xlfn.XLOOKUP(A5,'Hospitalisation Details'!$A$2:$A$2339,'Hospitalisation Details'!$G$2:$G$2339) -> tier - 1 | O5: =_xlfn.XLOOKUP(A5,'Hospitalisation Details'!$A$2:$A$2339,'Hospitalisation Details'!$H$2:$H$2339) -> tier - 3 | P5: =_xlfn.XLOOKUP(A5,'Hospitalisation Details'!$A$2:$A$2339,'Hospitalisation Details'!$I$2:$I$2339) -> R1024 | Q5: =_xlfn.XLOOKUP(A5,'Hospitalisation Details'!$A$2:$A$2339,'Hospitalisation Details'!$M$2:$M$2339) -> 32 | R5: =IF(Q5<20, "Young",IF(Q5<40,"Adult",IF(Q5<60, "Middle Aged", "Senior"))) -> Adult | T5: Average Charges | X5: 13529.92
A6: Id5 | B6: =_xlfn.XLOOKUP(A6,'Customer Names'!$A$2:$A$2336,'Customer Names'!$D$2:$D$2336) -> Kristyn | C6: =_xlfn.XLOOKUP(A6,'Midical Examination'!$A$2:$A$2336,'Midical Examination'!$B$2:$B$2336) -> 35.53 | D6: =_xlfn.XLOOKUP(A6,'Midical Examination'!$A$2:$A$2336,'Midical Examination'!$C$2:$C$2336) -> 5.45 | E6: =_xlfn.XLOOKUP(A6,'Midical Examination'!$A$2:$A$2336,'Midical Examination'!$D$2:$D$2336) -> No | F6: =_xlfn.XLOOKUP(A6,'Midical Examination'!$A$2:$A$2336,'Midical Examination'!$E$2:$E$2336) -> No | G6: =_xlfn.XLOOKUP(A6,'Midical Examination'!$A$2:$A$2336,'Midical Examination'!$F$2:$F$2336) -> No | H6: =_xlfn.XLOOKUP(A6,'Midical Examination'!$A$2:$A$2336,'Midical Examination'!$G$2:$G$2336) -> 0 | I6: =_xlfn.XLOOKUP(A6,'Midical Examination'!$A$2:$A$2336,'Midical Examination'!$H$2:$H$2336) -> yes | J6: =_xlfn.XLOOKUP(A6,'Midical Examination'!$A$2:$A$2336,'Midical Examination'!$I$2:$I$2336) -> Obesity | K6: =IF(D6<5.7, "Normal", IF(D6<6.5,"Pre-Diabetic", "Diabetic")) -> Normal | L6: =_xlfn.XLOOKUP(A6,'Hospitalisation Details'!$A$2:$A$2339,'Hospitalisation Details'!$L$2:$L$2339) -> 32678 | M6: =_xlfn.XLOOKUP(A6,'Hospitalisation Details'!$A$2:$A$2339,'Hospitalisation Details'!$F$2:$F$2339) -> 55135.4 | N6: =_xlfn.XLOOKUP(A6,'Hospitalisation Details'!$A$2:$A$2339,'Hospitalisation Details'!$G$2:$G$2339) -> tier - 1 | O6: =_xlfn.XLOOKUP(A6,'Hospitalisation Details'!$A$2:$A$2339,'Hospitalisation Details'!$H$2:$H$2339) -> tier - 2 | P6: =_xlfn.XLOOKUP(A6,'Hospitalisation Details'!$A$2:$A$2339,'Hospitalisation Details'!$I$2:$I$2339) -> R1012 | Q6: =_xlfn.XLOOKUP(A6,'Hospitalisation Details'!$A$2:$A$2339,'Hospitalisation Details'!$M$2:$M$2339) -> 33 | R6: =IF(Q6<20, "Young",IF(Q6<40,"Adult",IF(Q6<60, "Middle Aged", "Senior"))) -> Adult | T6: Average BMI | X6: 30.97
A7: Id6 | B7: =_xlfn.XLOOKUP(A7,'Customer Names'!$A$2:$A$2336,'Customer Names'!$D$2:$D$2336) -> Russell B | C7: =_xlfn.XLOOKUP(A7,'Midical Examination'!$A$2:$A$2336,'Midical Examination'!$B$2:$B$2336) -> 32.8 | D7: =_xlfn.XLOOKUP(A7,'Midical Examination'!$A$2:$A$2336,'Midical Examination'!$C$2:$C$2336) -> 6.59 | E7: =_xlfn.XLOOKUP(A7,'Midical Examination'!$A$2:$A$2336,'Midical Examination'!$D$2:$D$2336) -> No | F7: =_xlfn.XLOOKUP(A7,'Midical Examination'!$A$2:$A$2336,'Midical Examination'!$E$2:$E$2336) -> No | G7: =_xlfn.XLOOKUP(A7,'Midical Examination'!$A$2:$A$2336,'Midical Examination'!$F$2:$F$2336) -> No | H7: =_xlfn.XLOOKUP(A7,'Midical Examination'!$A$2:$A$2336,'Midical Examination'!$G$2:$G$2336) -> 0 | I7: =_xlfn.XLOOKUP(A7,'Midical Examination'!$A$2:$A$2336,'Midical Examination'!$H$2:$H$2336) -> yes | J7: =_xlfn.XLOOKUP(A7,'Midical Examination'!$A$2:$A$2336,'Midical Examination'!$I$2:$I$2336) -> Obesity | K7: =IF(D7<5.7, "Normal", IF(D7<6.5,"Pre-Diabetic", "Diabetic")) -> Diabetic | L7: =_xlfn.XLOOKUP(A7,'Hospitalisation Details'!$A$2:$A$2339,'Hospitalisation Details'!$L$2:$L$2339) -> 22862 | M7: =_xlfn.XLOOKUP(A7,'Hospitalisation Details'!$A$2:$A$2339,'Hospitalisation Details'!$F$2:$F$2339) -> 52590.83 | N7: =_xlfn.XLOOKUP(A7,'Hospitalisation Details'!$A$2:$A$2339,'Hospitalisation Details'!$G$2:$G$2339) -> tier - 1 | O7: =_xlfn.XLOOKUP(A7,'Hospitalisation Details'!$A$2:$A$2339,'Hospitalisation Details'!$H$2:$H$2339) -> tier - 3 | P7: =_xlfn.XLOOKUP(A7,'Hospitalisation Details'!$A$2:$A$2339,'Hospitalisation Details'!$I$2:$I$2339) -> R1011 | Q7: =_xlfn.XLOOKUP(A7,'Hospitalisation Details'!$A$2:$A$2339,'Hospitalisation Details'!$M$2:$M$2339) -> 60 | R7: =IF(Q7<20, "Young",IF(Q7<40,"Adult",IF(Q7<60, "Middle Aged", "Senior"))) -> Senior | T7: Average HBA1C | X7: 6.579
A8: Id7 | B8: =_xlfn.XLOOKUP(A8,'Customer Names'!$A$2:$A$2336,'Customer Names'!$D$2:$D$2336) -> Scott | C8: =_xlfn.XLOOKUP(A8,'Midical Examination'!$A$2:$A$2336,'Midical Examination'!$B$2:$B$2336) -> 36.4 | D8: =_xlfn.XLOOKUP(A8,'Midical Examination'!$A$2:$A$2336,'Midical Examination'!$C$2:$C$2336) -> 6.07 | E8: =_xlfn.XLOOKUP(A8,'Midical Examination'!$A$2:$A$2336,'Midical Examination'!$D$2:$D$2336) -> No | F8: =_xlfn.XLOOKUP(A8,'Midical Examination'!$A$2:$A$2336,'Midical Examination'!$E$2:$E$2336) -> No | G8: =_xlfn.XLOOKUP(A8,'Midical Examination'!$A$2:$A$2336,'Midical Examination'!$F$2:$F$2336) -> No | H8: =_xlfn.XLOOKUP(A8,'Midical Examination'!$A$2:$A$2336,'Midical Examination'!$G$2:$G$2336) -> 0 | I8: =_xlfn.XLOOKUP(A8,'Midical Examination'!$A$2:$A$2336,'Midical Examination'!$H$2:$H$2336) -> yes | J8: =_xlfn.XLOOKUP(A8,'Midical Examination'!$A$2:$A$2336,'Midical Examination'!$I$2:$I$2336) -> Obesity | K8: =IF(D8<5.7, "Normal", IF(D8<6.5,"Pre-Diabetic", "Diabetic")) -> Pre-Diabetic | L8: =_xlfn.XLOOKUP(A8,'Hospitalisation Details'!$A$2:$A$2339,'Hospitalisation Details'!$L$2:$L$2339) -> 34634 | M8: =_xlfn.XLOOKUP(A8,'Hospitalisation Details'!$A$2:$A$2339,'Hospitalisation Details'!$F$2:$F$2339) -> 51194.56 | N8: =_xlfn.XLOOKUP(A8,'Hospitalisation Details'!$A$2:$A$2339,'Hospitalisation Details'!$G$2:$G$2339) -> tier - 1 | O8: =_xlfn.XLOOKUP(A8,'Hospitalisation Details'!$A$2:$A$2339,'Hospitalisation Details'!$H$2:$H$2339) -> tier - 3 | P8: =_xlfn.XLOOKUP(A8,'Hospitalisation Details'!$A$2:$A$2339,'Hospitalisation Details'!$I$2:$I$2339) -> R1011 | Q8: =_xlfn.XLOOKUP(A8,'Hospitalisation Details'!$A$2:$A$2339,'Hospitalisation Details'!$M$2:$M$2339) -> 28 | R8: =IF(Q8<20, "Young",IF(Q8<40,"Adult",IF(Q8<60, "Middle Aged", "Senior"))) -> Adult | T8: Average Age | X8: 39
A9: Id8 | B9: =_xlfn.XLOOKUP(A9,'Customer Names'!$A$2:$A$2336,'Customer Names'!$D$2:$D$2336) -> Stephen | C9: =_xlfn.XLOOKUP(A9,'Midical Examination'!$A$2:$A$2336,'Midical Examination'!$B$2:$B$2336) -> 36.96 | D9: =_xlfn.XLOOKUP(A9,'Midical Examination'!$A$2:$A$2336,'Midical Examination'!$C$2:$C$2336) -> 7.93 | E9: =_xlfn.XLOOKUP(A9,'Midical Examination'!$A$2:$A$2336,'Midical Examination'!$D$2:$D$2336) -> No | F9: =_xlfn.XLOOKUP(A9,'Midical Examination'!$A$2:$A$2336,'Midical Examination'!$E$2:$E$2336) -> No | G9: =_xlfn.XLOOKUP(A9,'Midical Examination'!$A$2:$A$2336,'Midical Examination'!$F$2:$F$2336) -> No | H9: =_xlfn.XLOOKUP(A9,'Midical Examination'!$A$2:$A$2336,'Midical Examination'!$G$2:$G$2336) -> 3 | I9: =_xlfn.XLOOKUP(A9,'Midical Examination'!$A$2:$A$2336,'Midical Examination'!$H$2:$H$2336) -> yes | J9: =_xlfn.XLOOKUP(A9,'Midical Examination'!$A$2:$A$2336,'Midical Examination'!$I$2:$I$2336) -> Obesity | K9: =IF(D9<5.7, "Normal", IF(D9<6.5,"Pre-Diabetic", "Diabetic")) -> Diabetic | L9: =_xlfn.XLOOKUP(A9,'Hospitalisation Details'!$A$2:$A$2339,'Hospitalisation Details'!$L$2:$L$2339) -> 21363 | M9: =_xlfn.XLOOKUP(A9,'Hospitalisation Details'!$A$2:$A$2339,'Hospitalisation Details'!$F$2:$F$2339) -> 49577.66 | N9: =_xlfn.XLOOKUP(A9,'Hospitalisation Details'!$A$2:$A$2339,'Hospitalisation Details'!$G$2:$G$2339) -> tier - 2 | O9: =_xlfn.XLOOKUP(A9,'Hospitalisation Details'!$A$2:$A$2339,'Hospitalisation Details'!$H$2:$H$2339) -> tier - 2 | P9: =_xlfn.XLOOKUP(A9,'Hospitalisation Details'!$A$2:$A$2339,'Hospitalisation Details'!$I$2:$I$2339) -> R1013 | Q9: =_xlfn.XLOOKUP(A9,'Hospitalisation Details'!$A$2:$A$2339,'Hospitalisation Details'!$M$2:$M$2339) -> 64 | R9: =IF(Q9<20, "Young",IF(Q9<40,"Adult",IF(Q9<60, "Middle Aged", "Senior"))) -> Senior | T9: Average Surgeries | X9: 0.68
A10: Id9 | B10: =_xlfn.XLOOKUP(A10,'Customer Names'!$A$2:$A$2336,'Customer Names'!$D$2:$D$2336) -> Patrick R | C10: =_xlfn.XLOOKUP(A10,'Midical Examination'!$A$2:$A$2336,'Midical Examination'!$B$2:$B$2336) -> 41.14 | D10: =_xlfn.XLOOKUP(A10,'Midical Examination'!$A$2:$A$2336,'Midical Examination'!$C$2:$C$2336) -> 9.58 | E10: =_xlfn.XLOOKUP(A10,'Midical Examination'!$A$2:$A$2336,'Midical Examination'!$D$2:$D$2336) -> yes | F10: =_xlfn.XLOOKUP(A10,'Midical Examination'!$A$2:$A$2336,'Midical Examination'!$E$2:$E$2336) -> No | G10: =_xlfn.XLOOKUP(A10,'Midical Examination'!$A$2:$A$2336,'Midical Examination'!$F$2:$F$2336) -> Yes | H10: =_xlfn.XLOOKUP(A10,'Midical Examination'!$A$2:$A$2336,'Midical Examination'!$G$2:$G$2336) -> 1 | I10: =_xlfn.XLOOKUP(A10,'Midical Examination'!$A$2:$A$2336,'Midical Examination'!$H$2:$H$2336) -> yes | J10: =_xlfn.XLOOKUP(A10,'Midical Examination'!$A$2:$A$2336,'Midical Examination'!$I$2:$I$2336) -> Obesity | K10: =IF(D10<5.7, "Normal", IF(D10<6.5,"Pre-Diabetic", "Diabetic")) -> Diabetic | L10: =_xlfn.XLOOKUP(A10,'Hospitalisation Details'!$A$2:$A$2339,'Hospitalisation Details'!$L$2:$L$2339) -> 23258 | M10: =_xlfn.XLOOKUP(A10,'Hospitalisation Details'!$A$2:$A$2339,'Hospitalisation Details'!$F$2:$F$2339) -> 48970.25 | N10: =_xlfn.XLOOKUP(A10,'Hospitalisation Details'!$A$2:$A$2339,'Hospitalisation Details'!$G$2:$G$2339) -> tier - 1 | O10: =_xlfn.XLOOKUP(A10,'Hospitalisation Details'!$A$2:$A$2339,'Hospitalisation Details'!$H$2:$H$2339) -> tier - 2 | P10: =_xlfn.XLOOKUP(A10,'Hospitalisation Details'!$A$2:$A$2339,'Hospitalisation Details'!$I$2:$I$2339) -> R1013 | Q10: =_xlfn.XLOOKUP(A10,'Hospitalisation Details'!$A$2:$A$2339,'Hospitalisation Details'!$M$2:$M$2339) -> 59 | R10: =IF(Q10<20, "Young",IF(Q10<40,"Adult",IF(Q10<60, "Middle Aged", "Senior"))) -> Middle Aged | T10: Total healthcare costs | X10: 31592359
A11: Id10 | B11: =_xlfn.XLOOKUP(A11,'Customer Names'!$A$2:$A$2336,'Customer Names'!$D$2:$D$2336) -> Brooke N | C11: =_xlfn.XLOOKUP(A11,'Midical Examination'!$A$2:$A$2336,'Midical Examination'!$B$2:$B$2336) -> 38.06 | D11: =_xlfn.XLOOKUP(A11,'Midical Examination'!$A$2:$A$2336,'Midical Examination'!$C$2:$C$2336) -> 10.79 | E11: =_xlfn.XLOOKUP(A11,'Midical Examination'!$A$2:$A$2336,'Midical Examination'!$D$2:$D$2336) -> No | F11: =_xlfn.XLOOKUP(A11,'Midical Examination'!$A$2:$A$2336,'Midical Examination'!$E$2:$E$2336) -> No | G11: =_xlfn.XLOOKUP(A11,'Midical Examination'!$A$2:$A$2336,'Midical Examination'!$F$2:$F$2336) -> No | H11: =_xlfn.XLOOKUP(A11,'Midical Examination'!$A$2:$A$2336,'Midical Examination'!$G$2:$G$2336) -> 0 | I11: =_xlfn.XLOOKUP(A11,'Midical Examination'!$A$2:$A$2336,'Midical Examination'!$H$2:$H$2336) -> yes | J11: =_xlfn.XLOOKUP(A11,'Midical Examination'!$A$2:$A$2336,'Midical Examination'!$I$2:$I$2336) -> Obesity | K11: =IF(D11<5.7, "Normal", IF(D11<6.5,"Pre-Diabetic", "Diabetic")) -> Diabetic | L11: =_xlfn.XLOOKUP(A11,'Hospitalisation Details'!$A$2:$A$2339,'Hospitalisation Details'!$L$2:$L$2339) -> 28853 | M11: =_xlfn.XLOOKUP(A11,'Hospitalisation Details'!$A$2:$A$2339,'Hospitalisation Details'!$F$2:$F$2339) -> 48885.14 | N11: =_xlfn.XLOOKUP(A11,'Hospitalisation Details'!$A$2:$A$2339,'Hospitalisation Details'!$G$2:$G$2339) -> tier - 1 | O11: =_xlfn.XLOOKUP(A11,'Hospitalisation Details'!$A$2:$A$2339,'Hospitalisation Details'!$H$2:$H$2339) -> tier - 2 | P11: =_xlfn.XLOOKUP(A11,'Hospitalisation Details'!$A$2:$A$2339,'Hospitalisation Details'!$I$2:$I$2339) -> R1013 | Q11: =_xlfn.XLOOKUP(A11,'Hospitalisation Details'!$A$2:$A$2339,'Hospitalisation Details'!$M$2:$M$2339) -> 44 | R11: =IF(Q11<20, "Young",IF(Q11<40,"Adult",IF(Q11<60, "Middle Aged", "Senior"))) -> Middle Aged | T11: Total customers count | X11: 2335
A12: Id11 | B12: =_xlfn.XLOOKUP(A12,'Customer Names'!$A$2:$A$2336,'Customer Names'!$D$2:$D$2336) -> Paola Andrea | C12: =_xlfn.XLOOKUP(A12,'Midical Examination'!$A$2:$A$2336,'Midical Examination'!$B$2:$B$2336) -> 37.7 | D12: =_xlfn.XLOOKUP(A12,'Midical Examination'!$A$2:$A$2336,'Midical Examination'!$C$2:$C$2336) -> 5.96 | E12: =_xlfn.XLOOKUP(A12,'Midical Examination'!$A$2:$A$2336,'Midical Examination'!$D$2:$D$2336) -> yes | F12: =_xlfn.XLOOKUP(A12,'Midical Examination'!$A$2:$A$2336,'Midical Examination'!$E$2:$E$2336) -> No | G12: =_xlfn.XLOOKUP(A12,'Midical Examination'!$A$2:$A$2336,'Midical Examination'!$F$2:$F$2336) -> No | H12: =_xlfn.XLOOKUP(A12,'Midical Examination'!$A$2:$A$2336,'Midical Examination'!$G$2:$G$2336) -> 2 | I12: =_xlfn.XLOOKUP(A12,'Midical Examination'!$A$2:$A$2336,'Midical Examination'!$H$2:$H$2336) -> yes | J12: =_xlfn.XLOOKUP(A12,'Midical Examination'!$A$2:$A$2336,'Midical Examination'!$I$2:$I$2336) -> Obesity | K12: =IF(D12<5.7, "Normal", IF(D12<6.5,"Pre-Diabetic", "Diabetic")) -> Pre-Diabetic | L12: =_xlfn.XLOOKUP(A12,'Hospitalisation Details'!$A$2:$A$2339,'Hospitalisation Details'!$L$2:$L$2339) -> 21753 | M12: =_xlfn.XLOOKUP(A12,'Hospitalisation Details'!$A$2:$A$2339,'Hospitalisation Details'!$F$2:$F$2339) -> 48824.45 | N12: =_xlfn.XLOOKUP(A12,'Hospitalisation Details'!$A$2:$A$2339,'Hospitalisation Details'!$G$2:$G$2339) -> tier - 2 | O12: =_xlfn.XLOOKUP(A12,'Hospitalisation Details'!$A$2:$A$2339,'Hospitalisation Details'!$H$2:$H$2339) -> tier - 1 | P12: =_xlfn.XLOOKUP(A12,'Hospitalisation Details'!$A$2:$A$2339,'Hospitalisation Details'!$I$2:$I$2339) -> R1011 | Q12: =_xlfn.XLOOKUP(A12,'Hospitalisation Details'!$A$2:$A$2339,'Hospitalisation Details'!$M$2:$M$2339) -> 63 | R12: =IF(Q12<20, "Young",IF(Q12<40,"Adult",IF(Q12<60, "Middle Aged", "Senior"))) -> Senior | T12: Total hospitalisation count | X12: 2338
A13: Id12 | B13: =_xlfn.XLOOKUP(A13,'Customer Names'!$A$2:$A$2336,'Customer Names'!$D$2:$D$2336) -> David | C13: =_xlfn.XLOOKUP(A13,'Midical Examination'!$A$2:$A$2336,'Midical Examination'!$B$2:$B$2336) -> 42.13 | D13: =_xlfn.XLOOKUP(A13,'Midical Examination'!$A$2:$A$2336,'Midical Examination'!$C$2:$C$2336) -> 11.9 | E13: =_xlfn.XLOOKUP(A13,'Midical Examination'!$A$2:$A$2336,'Midical Examination'!$D$2:$D$2336) -> No | F13: =_xlfn.XLOOKUP(A13,'Midical Examination'!$A$2:$A$2336,'Midical Examination'!$E$2:$E$2336) -> No | G13: =_xlfn.XLOOKUP(A13,'Midical Examination'!$A$2:$A$2336,'Midical Examination'!$F$2:$F$2336) -> No | H13: =_xlfn.XLOOKUP(A13,'Midical Examination'!$A$2:$A$2336,'Midical Examination'!$G$2:$G$2336) -> 0 | I13: =_xlfn.XLOOKUP(A13,'Midical Examination'!$A$2:$A$2336,'Midical Examination'!$H$2:$H$2336) -> yes | J13: =_xlfn.XLOOKUP(A13,'Midical Examination'!$A$2:$A$2336,'Midical Examination'!$I$2:$I$2336) -> Obesity | K13: =IF(D13<5.7, "Normal", IF(D13<6.5,"Pre-Diabetic", "Diabetic")) -> Diabetic | L13: =_xlfn.XLOOKUP(A13,'Hospitalisation Details'!$A$2:$A$2339,'Hospitalisation Details'!$L$2:$L$2339) -> 24042 | M13: =_xlfn.XLOOKUP(A13,'Hospitalisation Details'!$A$2:$A$2339,'Hospitalisation Details'!$F$2:$F$2339) -> 48675.52 | N13: =_xlfn.XLOOKUP(A13,'Hospitalisation Details'!$A$2:$A$2339,'Hospitalisation Details'!$G$2:$G$2339) -> tier - 1 | O13: =_xlfn.XLOOKUP(A13,'Hospitalisation Details'!$A$2:$A$2339,'Hospitalisation Details'!$H$2:$H$2339) -> tier - 2 | P13: =_xlfn.XLOOKUP(A13,'Hospitalisation Details'!$A$2:$A$2339,'Hospitalisation Details'!$I$2:$I$2339) -> R1013 | Q13: =_xlfn.XLOOKUP(A13,'Hospitalisation Details'!$A$2:$A$2339,'Hospitalisation Details'!$M$2:$M$2339) -> 57 | R13: =IF(Q13<20, "Young",IF(Q13<40,"Adult",IF(Q13<60, "Middle Aged", "Senior"))) -> Middle Aged
A14: Id13 | B14: =_xlfn.XLOOKUP(A14,'Customer Names'!$A$2:$A$2336,'Customer Names'!$D$2:$D$2336) -> Wade | C14: =_xlfn.XLOOKUP(A14,'Midical Examination'!$A$2:$A$2336,'Midical Examination'!$B$2:$B$2336) -> 40.92 | D14: =_xlfn.XLOOKUP(A14,'Midical Examination'!$A$2:$A$2336,'Midical Examination'!$C$2:$C$2336) -> 8.41 | E14: =_xlfn.XLOOKUP(A14,'Midical Examination'!$A$2:$A$2336,'Midical Examination'!$D$2:$D$2336) -> No | F14: =_xlfn.XLOOKUP(A14,'Midical Examination'!$A$2:$A$2336,'Midical Examination'!$E$2:$E$2336) -> No | G14: =_xlfn.XLOOKUP(A14,'Midical Examination'!$A$2:$A$2336,'Midical Examination'!$F$2:$F$2336) -> No | H14: =_xlfn.XLOOKUP(A14,'Midical Examination'!$A$2:$A$2336,'Midical Examination'!$G$2:$G$2336) -> 0 | I14: =_xlfn.XLOOKUP(A14,'Midical Examination'!$A$2:$A$2336,'Midical Examination'!$H$2:$H$2336) -> yes | J14: =_xlfn.XLOOKUP(A14,'Midical Examination'!$A$2:$A$2336,'Midical Examination'!$I$2:$I$2336) -> Obesity | K14: =IF(D14<5.7, "Normal", IF(D14<6.5,"Pre-Diabetic", "Diabetic")) -> Diabetic | L14: =_xlfn.XLOOKUP(A14,'Hospitalisation Details'!$A$2:$A$2339,'Hospitalisation Details'!$L$2:$L$2339) -> 22930 | M14: =_xlfn.XLOOKUP(A14,'Hospitalisation Details'!$A$2:$A$2339,'Hospitalisation Details'!$F$2:$F$2339) -> 48673.56 | N14: =_xlfn.XLOOKUP(A14,'Hospitalisation Details'!$A$2:$A$2339,'Hospitalisation Details'!$G$2:$G$2339) -> tier - 1 | O14: =_xlfn.XLOOKUP(A14,'Hospitalisation Details'!$A$2:$A$2339,'Hospitalisation Details'!$H$2:$H$2339) -> tier - 2 | P14: =_xlfn.XLOOKUP(A14,'Hospitalisation Details'!$A$2:$A$2339,'Hospitalisation Details'!$I$2:$I$2339) -> R1013 | Q14: =_xlfn.XLOOKUP(A14,'Hospitalisation Details'!$A$2:$A$2339,'Hospitalisation Details'!$M$2:$M$2339) -> 60 | R14: =IF(Q14<20, "Young",IF(Q14<40,"Adult",IF(Q14<60, "Middle Aged", "Senior"))) -> Senior
A15: Id14 | B15: =_xlfn.XLOOKUP(A15,'Customer Names'!$A$2:$A$2336,'Customer Names'!$D$2:$D$2336) -> Franklin | C15: =_xlfn.XLOOKUP(A15,'Midical Examination'!$A$2:$A$2336,'Midical Examination'!$B$2:$B$2336) -> 40.565 | D15: =_xlfn.XLOOKUP(A15,'Midical Examination'!$A$2:$A$2336,'Midical Examination'!$C$2:$C$2336) -> 7.02 | E15: =_xlfn.XLOOKUP(A15,'Midical Examination'!$A$2:$A$2336,'Midical Examination'!$D$2:$D$2336) -> No | F15: =_xlfn.XLOOKUP(A15,'Midical Examination'!$A$2:$A$2336,'Midical Examination'!$E$2:$E$2336) -> No | G15: =_xlfn.XLOOKUP(A15,'Midical Examination'!$A$2:$A$2336,'Midical Examination'!$F$2:$F$2336) -> No | H15: =_xlfn.XLOOKUP(A15,'Midical Examination'!$A$2:$A$2336,'Midical Examination'!$G$2:$G$2336) -> 0 | I15: =_xlfn.XLOOKUP(A15,'Midical Examination'!$A$2:$A$2336,'Midical Examination'!$H$2:$H$2336) -> yes | J15: =_xlfn.XLOOKUP(A15,'Midical Examination'!$A$2:$A$2336,'Midical Examination'!$I$2:$I$2336) -> Obesity | K15: =IF(D15<5.7, "Normal", IF(D15<6.5,"Pre-Diabetic", "Diabetic")) -> Diabetic | L15: =_xlfn.XLOOKUP(A15,'Hospitalisation Details'!$A$2:$A$2339,'Hospitalisation Details'!$L$2:$L$2339) -> 25173 | M15: =_xlfn.XLOOKUP(A15,'Hospitalisation Details'!$A$2:$A$2339,'Hospitalisation Details'!$F$2:$F$2339) -> 48549.18 | N15: =_xlfn.XLOOKUP(A15,'Hospitalisation Details'!$A$2:$A$2339,'Hospitalisation Details'!$G$2:$G$2339) -> tier - 1 | O15: =_xlfn.XLOOKUP(A15,'Hospitalisation Details'!$A$2:$A$2339,'Hospitalisation Details'!$H$2:$H$2339) -> tier - 3 | P15: =_xlfn.XLOOKUP(A15,'Hospitalisation Details'!$A$2:$A$2339,'Hospitalisation Details'!$I$2:$I$2339) -> R1016 | Q15: =_xlfn.XLOOKUP(A15,'Hospitalisation Details'!$A$2:$A$2339,'Hospitalisation Details'!$M$2:$M$2339) -> 54 | R15: =IF(Q15<20, "Young",IF(Q15<40,"Adult",IF(Q15<60, "Middle Aged", "Senior"))) -> Middle Aged
A16: Id15 | B16: =_xlfn.XLOOKUP(A16,'Customer Names'!$A$2:$A$2336,'Customer Names'!$D$2:$D$2336) -> Leilani M | C16: =_xlfn.XLOOKUP(A16,'Midical Examination'!$A$2:$A$2336,'Midical Examination'!$B$2:$B$2336) -> 36.385 | D16: =_xlfn.XLOOKUP(A16,'Midical Examination'!$A$2:$A$2336,'Midical Examination'!$C$2:$C$2336) -> 7.59 | E16: =_xlfn.XLOOKUP(A16,'Midical Examination'!$A$2:$A$2336,'Midical Examination'!$D$2:$D$2336) -> yes | F16: =_xlfn.XLOOKUP(A16,'Midical Examination'!$A$2:$A$2336,'Midical Examination'!$E$2:$E$2336) -> No | G16: =_xlfn.XLOOKUP(A16,'Midical Examination'!$A$2:$A$2336,'Midical Examination'!$F$2:$F$2336) -> No | H16: =_xlfn.XLOOKUP(A16,'Midical Examination'!$A$2:$A$2336,'Midical Examination'!$G$2:$G$2336) -> 2 | I16: =_xlfn.XLOOKUP(A16,'Midical Examination'!$A$2:$A$2336,'Midical Examination'!$H$2:$H$2336) -> yes | J16: =_xlfn.XLOOKUP(A16,'Midical Examination'!$A$2:$A$2336,'Midical Examination'!$I$2:$I$2336) -> Obesity | K16: =IF(D16<5.7, "Normal", IF(D16<6.5,"Pre-Diabetic", "Diabetic")) -> Diabetic | L16: =_xlfn.XLOOKUP(A16,'Hospitalisation Details'!$A$2:$A$2339,'Hospitalisation Details'!$L$2:$L$2339) -> 22636 | M16: =_xlfn.XLOOKUP(A16,'Hospitalisation Details'!$A$2:$A$2339,'Hospitalisation Details'!$F$2:$F$2339) -> 48517.56 | N16: =_xlfn.XLOOKUP(A16,'Hospitalisation Details'!$A$2:$A$2339,'Hospitalisation Details'!$G$2:$G$2339) -> tier - 1 | O16: =_xlfn.XLOOKUP(A16,'Hospitalisation Details'!$A$2:$A$2339,'Hospitalisation Details'!$H$2:$H$2339) -> tier - 3 | P16: =_xlfn.XLOOKUP(A16,'Hospitalisation Details'!$A$2:$A$2339,'Hospitalisation Details'!$I$2:$I$2339) -> R1024 | Q16: =_xlfn.XLOOKUP(A16,'Hospitalisation Details'!$A$2:$A$2339,'Hospitalisation Details'!$M$2:$M$2339) -> 61 | R16: =IF(Q16<20, "Young",IF(Q16<40,"Adult",IF(Q16<60, "Middle Aged", "Senior"))) -> Senior
A17: Id16 | B17: =_xlfn.XLOOKUP(A17,'Customer Names'!$A$2:$A$2336,'Customer Names'!$D$2:$D$2336) -> Philippe | C17: =_xlfn.XLOOKUP(A17,'Midical Examination'!$A$2:$A$2336,'Midical Examination'!$B$2:$B$2336) -> 39.9 | D17: =_xlfn.XLOOKUP(A17,'Midical Examination'!$A$2:$A$2336,'Midical Examination'!$C$2:$C$2336) -> 11.32 | E17: =_xlfn.XLOOKUP(A17,'Midical Examination'!$A$2:$A$2336,'Midical Examination'!$D$2:$D$2336) -> No | F17: =_xlfn.XLOOKUP(A17,'Midical Examination'!$A$2:$A$2336,'Midical Examination'!$E$2:$E$2336) -> No | G17: =_xlfn.XLOOKUP(A17,'Midical Examination'!$A$2:$A$2336,'Midical Examination'!$F$2:$F$2336) -> No | H17: =_xlfn.XLOOKUP(A17,'Midical Examination'!$A$2:$A$2336,'Midical Examination'!$G$2:$G$2336) -> 0 | I17: =_xlfn.XLOOKUP(A17,'Midical Examination'!$A$2:$A$2336,'Midical Examination'!$H$2:$H$2336) -> yes | J17: =_xlfn.XLOOKUP(A17,'Midical Examination'!$A$2:$A$2336,'Midical Examination'!$I$2:$I$2336) -> Obesity | K17: =IF(D17<5.7, "Normal", IF(D17<6.5,"Pre-Diabetic", "Diabetic")) -> Diabetic | L17: =_xlfn.XLOOKUP(A17,'Hospitalisation Details'!$A$2:$A$2339,'Hospitalisation Details'!$L$2:$L$2339) -> 22885 | M17: =_xlfn.XLOOKUP(A17,'Hospitalisation Details'!$A$2:$A$2339,'Hospitalisation Details'!$F$2:$F$2339) -> 48173.36 | N17: =_xlfn.XLOOKUP(A17,'Hospitalisation Details'!$A$2:$A$2339,'Hospitalisation Details'!$G$2:$G$2339) -> tier - 1 | O17: =_xlfn.XLOOKUP(A17,'Hospitalisation Details'!$A$2:$A$2339,'Hospitalisation Details'!$H$2:$H$2339) -> tier - 3 | P17: =_xlfn.XLOOKUP(A17,'Hospitalisation Details'!$A$2:$A$2339,'Hospitalisation Details'!$I$2:$I$2339) -> R1011 | Q17: =_xlfn.XLOOKUP(A17,'Hospitalisation Details'!$A$2:$A$2339,'Hospitalisation Details'!$M$2:$M$2339) -> 60 | R17: =IF(Q17<20, "Young",IF(Q17<40,"Adult",IF(Q17<60, "Middle Aged", "Senior"))) -> Senior
A18: Id17 | B18: =_xlfn.XLOOKUP(A18,'Customer Names'!$A$2:$A$2336,'Customer Names'!$D$2:$D$2336) -> Jennifer A | C18: =_xlfn.XLOOKUP(A18,'Midical Examination'!$A$2:$A$2336,'Midical Examination'!$B$2:$B$2336) -> 33.8 | D18: =_xlfn.XLOOKUP(A18,'Midical Examination'!$A$2:$A$2336,'Midical Examination'!$C$2:$C$2336) -> 7.67 | E18: =_xlfn.XLOOKUP(A18,'Midical Examination'!$A$2:$A$2336,'Midical Examination'!$D$2:$D$2336) -> No | F18: =_xlfn.XLOOKUP(A18,'Midical Examination'!$A$2:$A$2336,'Midical Examination'!$E$2:$E$2336) -> No | G18: =_xlfn.XLOOKUP(A18,'Midical Examination'!$A$2:$A$2336,'Midical Examination'!$F$2:$F$2336) -> No | H18: =_xlfn.XLOOKUP(A18,'Midical Examination'!$A$2:$A$2336,'Midical Examination'!$G$2:$G$2336) -> 3 | I18: =_xlfn.XLOOKUP(A18,'Midical Examination'!$A$2:$A$2336,'Midical Examination'!$H$2:$H$2336) -> yes | J18: =_xlfn.XLOOKUP(A18,'Midical Examination'!$A$2:$A$2336,'Midical Examination'!$I$2:$I$2336) -> Obesity | K18: =IF(D18<5.7, "Normal", IF(D18<6.5,"Pre-Diabetic", "Diabetic")) -> Diabetic | L18: =_xlfn.XLOOKUP(A18,'Hospitalisation Details'!$A$2:$A$2339,'Hospitalisation Details'!$L$2:$L$2339) -> 21505 | M18: =_xlfn.XLOOKUP(A18,'Hospitalisation Details'!$A$2:$A$2339,'Hospitalisation Details'!$F$2:$F$2339) -> 47928.03 | N18: =_xlfn.XLOOKUP(A18,'Hospitalisation Details'!$A$2:$A$2339,'Hospitalisation Details'!$G$2:$G$2339) -> tier - 2 | O18: =_xlfn.XLOOKUP(A18,'Hospitalisation Details'!$A$2:$A$2339,'Hospitalisation Details'!$H$2:$H$2339) -> tier - 3 | P18: =_xlfn.XLOOKUP(A18,'Hospitalisation Details'!$A$2:$A$2339,'Hospitalisation Details'!$I$2:$I$2339) -> R1011 | Q18: =_xlfn.XLOOKUP(A18,'Hospitalisation Details'!$A$2:$A$2339,'Hospitalisation Details'!$M$2:$M$2339) -> 64 | R18: =IF(Q18<20, "Young",IF(Q18<40,"Adult",IF(Q18<60, "Middle Aged", "Senior"))) -> Senior
A19: Id18 | B19: =_xlfn.XLOOKUP(A19,'Customer Names'!$A$2:$A$2336,'Customer Names'!$D$2:$D$2336) -> Christina M | C19: =_xlfn.XLOOKUP(A19,'Midical Examination'!$A$2:$A$2336,'Midical Examination'!$B$2:$B$2336) -> 36.765 | D19: =_xlfn.XLOOKUP(A19,'Midical Examination'!$A$2:$A$2336,'Midical Examination'!$C$2:$C$2336) -> 7.29 | E19: =_xlfn.XLOOKUP(A19,'Midical Examination'!$A$2:$A$2336,'Midical Examination'!$D$2:$D$2336) -> yes | F19: =_xlfn.XLOOKUP(A19,'Midical Examination'!$A$2:$A$2336,'Midical Examination'!$E$2:$E$2336) -> No | G19: =_xlfn.XLOOKUP(A19,'Midical Examination'!$A$2:$A$2336,'Midical Examination'!$F$2:$F$2336) -> Yes | H19: =_xlfn.XLOOKUP(A19,'Midical Examination'!$A$2:$A$2336,'Midical Examination'!$G$2:$G$2336) -> 1 | I19: =_xlfn.XLOOKUP(A19,'Midical Examination'!$A$2:$A$2336,'Midical Examination'!$H$2:$H$2336) -> yes | J19: =_xlfn.XLOOKUP(A19,'Midical Examination'!$A$2:$A$2336,'Midical Examination'!$I$2:$I$2336) -> Obesity | K19: =IF(D19<5.7, "Normal", IF(D19<6.5,"Pre-Diabetic", "Diabetic")) -> Diabetic | L19: =_xlfn.XLOOKUP(A19,'Hospitalisation Details'!$A$2:$A$2339,'Hospitalisation Details'!$L$2:$L$2339) -> 23228 | M19: =_xlfn.XLOOKUP(A19,'Hospitalisation Details'!$A$2:$A$2339,'Hospitalisation Details'!$F$2:$F$2339) -> 47896.79 | N19: =_xlfn.XLOOKUP(A19,'Hospitalisation Details'!$A$2:$A$2339,'Hospitalisation Details'!$G$2:$G$2339) -> tier - 1 | O19: =_xlfn.XLOOKUP(A19,'Hospitalisation Details'!$A$2:$A$2339,'Hospitalisation Details'!$H$2:$H$2339) -> tier - 3 | P19: =_xlfn.XLOOKUP(A19,'Hospitalisation Details'!$A$2:$A$2339,'Hospitalisation Details'!$I$2:$I$2339) -> R1024 | Q19: =_xlfn.XLOOKUP(A19,'Hospitalisation Details'!$A$2:$A$2339,'Hospitalisation Details'!$M$2:$M$2339) -> 59 | R19: =IF(Q19<20, "Young",IF(Q19<40,"Adult",IF(Q19<60, "Middle Aged", "Senior"))) -> Middle Aged
A20: Id19 | B20: =_xlfn.XLOOKUP(A20,'Customer Names'!$A$2:$A$2336,'Customer Names'!$D$2:$D$2336) -> Said Sr | C20: =_xlfn.XLOOKUP(A20,'Midical Examination'!$A$2:$A$2336,'Midical Examination'!$B$2:$B$2336) -> 36.955 | D20: =_xlfn.XLOOKUP(A20,'Midical Examination'!$A$2:$A$2336,'Midical Examination'!$C$2:$C$2336) -> 4.72 | E20: =_xlfn.XLOOKUP(A20,'Midical Examination'!$A$2:$A$2336,'Midical Examination'!$D$2:$D$2336) -> yes | F20: =_xlfn.XLOOKUP(A20,'Midical Examination'!$A$2:$A$2336,'Midical Examination'!$E$2:$E$2336) -> No | G20: =_xlfn.XLOOKUP(A20,'Midical Examination'!$A$2:$A$2336,'Midical Examination'!$F$2:$F$2336) -> No | H20: =_xlfn.XLOOKUP(A20,'Midical Examination'!$A$2:$A$2336,'Midical Examination'!$G$2:$G$2336) -> 1 | I20: =_xlfn.XLOOKUP(A20,'Midical Examination'!$A$2:$A$2336,'Midical Examination'!$H$2:$H$2336) -> yes | J20: =_xlfn.XLOOKUP(A20,'Midical Examination'!$A$2:$A$2336,'Midical Examination'!$I$2:$I$2336) -> Obesity | K20: =IF(D20<5.7, "Normal", IF(D20<6.5,"Pre-Diabetic", "Diabetic")) -> Normal | L20: =_xlfn.XLOOKUP(A20,'Hospitalisation Details'!$A$2:$A$2339,'Hospitalisation Details'!$L$2:$L$2339) -> 23688 | M20: =_xlfn.XLOOKUP(A20,'Hospitalisation Details'!$A$2:$A$2339,'Hospitalisation Details'!$F$2:$F$2339) -> 47496.49 | N20: =_xlfn.XLOOKUP(A20,'Hospitalisation Details'!$A$2:$A$2339,'Hospitalisation Details'!$G$2:$G$2339) -> tier - 1 | O20: =_xlfn.XLOOKUP(A20,'Hospitalisation Details'!$A$2:$A$2339,'Hospitalisation Details'!$H$2:$H$2339) -> tier - 3 | P20: =_xlfn.XLOOKUP(A20,'Hospitalisation Details'!$A$2:$A$2339,'Hospitalisation Details'!$I$2:$I$2339) -> R1012 | Q20: =_xlfn.XLOOKUP(A20,'Hospitalisation Details'!$A$2:$A$2339,'Hospitalisation Details'!$M$2:$M$2339) -> 58 | R20: =IF(Q20<20, "Young",IF(Q20<40,"Adult",IF(Q20<60, "Middle Aged", "Senior"))) -> Middle Aged
A21: Id20 | B21: =_xlfn.XLOOKUP(A21,'Customer Names'!$A$2:$A$2336,'Customer Names'!$D$2:$D$2336) -> John | C21: =_xlfn.XLOOKUP(A21,'Midical Examination'!$A$2:$A$2336,'Midical Examination'!$B$2:$B$2336) -> 42.9 | D21: =_xlfn.XLOOKUP(A21,'Midical Examination'!$A$2:$A$2336,'Midical Examination'!$C$2:$C$2336) -> 11.41 | E21: =_xlfn.XLOOKUP(A21,'Midical Examination'!$A$2:$A$2336,'Midical Examination'!$D$2:$D$2336) -> No | F21: =_xlfn.XLOOKUP(A21,'Midical Examination'!$A$2:$A$2336,'Midical Examination'!$E$2:$E$2336) -> No | G21: =_xlfn.XLOOKUP(A21,'Midical Examination'!$A$2:$A$2336,'Midical Examination'!$F$2:$F$2336) -> No | H21: =_xlfn.XLOOKUP(A21,'Midical Examination'!$A$2:$A$2336,'Midical Examination'!$G$2:$G$2336) -> 0 | I21: =_xlfn.XLOOKUP(A21,'Midical Examination'!$A$2:$A$2336,'Midical Examination'!$H$2:$H$2336) -> yes | J21: =_xlfn.XLOOKUP(A21,'Midical Examination'!$A$2:$A$2336,'Midical Examination'!$I$2:$I$2336) -> Obesity | K21: =IF(D21<5.7, "Normal", IF(D21<6.5,"Pre-Diabetic", "Diabetic")) -> Diabetic | L21: =_xlfn.XLOOKUP(A21,'Hospitalisation Details'!$A$2:$A$2339,'Hospitalisation Details'!$L$2:$L$2339) -> 26203 | M21: =_xlfn.XLOOKUP(A21,'Hospitalisation Details'!$A$2:$A$2339,'Hospitalisation Details'!$F$2:$F$2339) -> 47462.89 | N21: =_xlfn.XLOOKUP(A21,'Hospitalisation Details'!$A$2:$A$2339,'Hospitalisation Details'!$G$2:$G$2339) -> tier - 1 | O21: =_xlfn.XLOOKUP(A21,'Hospitalisation Details'!$A$2:$A$2339,'Hospitalisation Details'!$H$2:$H$2339) -> tier - 2 | P21: =_xlfn.XLOOKUP(A21,'Hospitalisation Details'!$A$2:$A$2339,'Hospitalisation Details'!$I$2:$I$2339) -> R1013 | Q21: =_xlfn.XLOOKUP(A21,'Hospitalisation Details'!$A$2:$A$2339,'Hospitalisation Details'!$M$2:$M$2339) -> 51 | R21: =IF(Q21<20, "Young",IF(Q21<40,"Adult",IF(Q21<60, "Middle Aged", "Senior"))) -> Middle Aged
A22: Id21 | B22: =_xlfn.XLOOKUP(A22,'Customer Names'!$A$2:$A$2336,'Customer Names'!$D$2:$D$2336) -> Myles | C22: =_xlfn.XLOOKUP(A22,'Midical Examination'!$A$2:$A$2336,'Midical Examination'!$B$2:$B$2336) -> 36.3 | D22: =_xlfn.XLOOKUP(A22,'Midical Examination'!$A$2:$A$2336,'Midical Examination'!$C$2:$C$2336) -> 11.5 | E22: =_xlfn.XLOOKUP(A22,'Midical Examination'!$A$2:$A$2336,'Midical Examination'!$D$2:$D$2336) -> yes | F22: =_xlfn.XLOOKUP(A22,'Midical Examination'!$A$2:$A$2336,'Midical Examination'!$E$2:$E$2336) -> No | G22: =_xlfn.XLOOKUP(A22,'Midical Examination'!$A$2:$A$2336,'Midical Examination'!$F$2:$F$2336) -> No | H22: =_xlfn.XLOOKUP(A22,'Midical Examination'!$A$2:$A$2336,'Midical Examination'!$G$2:$G$2336) -> 2 | I22: =_xlfn.XLOOKUP(A22,'Midical Examination'!$A$2:$A$2336,'Midical Examination'!$H$2:$H$2336) -> yes | J22: =_xlfn.XLOOKUP(A22,'Midical Examination'!$A$2:$A$2336,'Midical Examination'!$I$2:$I$2336) -> Obesity | K22: =IF(D22<5.7, "Normal", IF(D22<6.5,"Pre-Diabetic", "Diabetic")) -> Diabetic | L22: =_xlfn.XLOOKUP(A22,'Hospitalisation Details'!$A$2:$A$2339,'Hospitalisation Details'!$L$2:$L$2339) -> 22445 | M22: =_xlfn.XLOOKUP(A22,'Hospitalisation Details'!$A$2:$A$2339,'Hospitalisation Details'!$F$2:$F$2339) -> 47403.88 | N22: =_xlfn.XLOOKUP(A22,'Hospitalisation Details'!$A$2:$A$2339,'Hospitalisation Details'!$G$2:$G$2339) -> tier - 1 | O22: =_xlfn.XLOOKUP(A22,'Hospitalisation Details'!$A$2:$A$2339,'Hospitalisation Details'!$H$2:$H$2339) -> tier - 3 | P22: =_xlfn.XLOOKUP(A22,'Hospitalisation Details'!$A$2:$A$2339,'Hospitalisation Details'!$I$2:$I$2339) -> R1011 | Q22: =_xlfn.XLOOKUP(A22,'Hospitalisation Details'!$A$2:$A$2339,'Hospitalisation Details'!$M$2:$M$2339) -> 61 | R22: =IF(Q22<20, "Young",IF(Q22<40,"Adult",IF(Q22<60, "Middle Aged", "Senior"))) -> Senior
A23: Id22 | B23: =_xlfn.XLOOKUP(A23,'Customer Names'!$A$2:$A$2336,'Customer Names'!$D$2:$D$2336) -> Madelyn C | C23: =_xlfn.XLOOKUP(A23,'Midical Examination'!$A$2:$A$2336,'Midical Examination'!$B$2:$B$2336) -> 32.2 | D23: =_xlfn.XLOOKUP(A23,'Midical Examination'!$A$2:$A$2336,'Midical Examination'!$C$2:$C$2336) -> 6.22 | E23: =_xlfn.XLOOKUP(A23,'Midical Examination'!$A$2:$A$2336,'Midical Examination'!$D$2:$D$2336) -> yes | F23: =_xlfn.XLOOKUP(A23,'Midical Examination'!$A$2:$A$2336,'Midical Examination'!$E$2:$E$2336) -> No | G23: =_xlfn.XLOOKUP(A23,'Midical Examination'!$A$2:$A$2336,'Midical Examination'!$F$2:$F$2336) -> No | H23: =_xlfn.XLOOKUP(A23,'Midical Examination'!$A$2:$A$2336,'Midical Examination'!$G$2:$G$2336) -> 2 | I23: =_xlfn.XLOOKUP(A23,'Midical Examination'!$A$2:$A$2336,'Midical Examination'!$H$2:$H$2336) -> yes | J23: =_xlfn.XLOOKUP(A23,'Midical Examination'!$A$2:$A$2336,'Midical Examination'!$I$2:$I$2336) -> Obesity | K23: =IF(D23<5.7, "Normal", IF(D23<6.5,"Pre-Diabetic", "Diabetic")) -> Pre-Diabetic | L23: =_xlfn.XLOOKUP(A23,'Hospitalisation Details'!$A$2:$A$2339,'Hospitalisation Details'!$L$2:$L$2339) -> 21827 | M23: =_xlfn.XLOOKUP(A23,'Hospitalisation Details'!$A$2:$A$2339,'Hospitalisation Details'!$F$2:$F$2339) -> 47305.31 | N23: =_xlfn.XLOOKUP(A23,'Hospitalisation Details'!$A$2:$A$2339,'Hospitalisation Details'!$G$2:$G$2339) -> tier - 2 | O23: =_xlfn.XLOOKUP(A23,'Hospitalisation Details'!$A$2:$A$2339,'Hospitalisation Details'!$H$2:$H$2339) -> tier - 1 | P23: =_xlfn.XLOOKUP(A23,'Hospitalisation Details'!$A$2:$A$2339,'Hospitalisation Details'!$I$2:$I$2339) -> R1011 | Q23: =_xlfn.XLOOKUP(A23,'Hospitalisation Details'!$A$2:$A$2339,'Hospitalisation Details'!$M$2:$M$2339) -> 63 | R23: =IF(Q23<20, "Young",IF(Q23<40,"Adult",IF(Q23<60, "Middle Aged", "Senior"))) -> Senior
A24: Id23 | B24: =_xlfn.XLOOKUP(A24,'Customer Names'!$A$2:$A$2336,'Customer Names'!$D$2:$D$2336) -> Nicole | C24: =_xlfn.XLOOKUP(A24,'Midical Examination'!$A$2:$A$2336,'Midical Examination'!$B$2:$B$2336) -> 31.3 | D24: =_xlfn.XLOOKUP(A24,'Midical Examination'!$A$2:$A$2336,'Midical Examination'!$C$2:$C$2336) -> 11.38 | E24: =_xlfn.XLOOKUP(A24,'Midical Examination'!$A$2:$A$2336,'Midical Examination'!$D$2:$D$2336) -> No | F24: =_xlfn.XLOOKUP(A24,'Midical Examination'!$A$2:$A$2336,'Midical Examination'!$E$2:$E$2336) -> No | G24: =_xlfn.XLOOKUP(A24,'Midical Examination'!$A$2:$A$2336,'Midical Examination'!$F$2:$F$2336) -> No | H24: =_xlfn.XLOOKUP(A24,'Midical Examination'!$A$2:$A$2336,'Midical Examination'!$G$2:$G$2336) -> 3 | I24: =_xlfn.XLOOKUP(A24,'Midical Examination'!$A$2:$A$2336,'Midical Examination'!$H$2:$H$2336) -> yes | J24: =_xlfn.XLOOKUP(A24,'Midical Examination'!$A$2:$A$2336,'Midical Examination'!$I$2:$I$2336) -> Obesity | K24: =IF(D24<5.7, "Normal", IF(D24<6.5,"Pre-Diabetic", "Diabetic")) -> Diabetic | L24: =_xlfn.XLOOKUP(A24,'Hospitalisation Details'!$A$2:$A$2339,'Hospitalisation Details'!$L$2:$L$2339) -> 21431 | M24: =_xlfn.XLOOKUP(A24,'Hospitalisation Details'!$A$2:$A$2339,'Hospitalisation Details'!$F$2:$F$2339) -> 47291.06 | N24: =_xlfn.XLOOKUP(A24,'Hospitalisation Details'!$A$2:$A$2339,'Hospitalisation Details'!$G$2:$G$2339) -> tier - 2 | O24: =_xlfn.XLOOKUP(A24,'Hospitalisation Details'!$A$2:$A$2339,'Hospitalisation Details'!$H$2:$H$2339) -> tier - 1 | P24: =_xlfn.XLOOKUP(A24,'Hospitalisation Details'!$A$2:$A$2339,'Hospitalisation Details'!$I$2:$I$2339) -> R1011 | Q24: =_xlfn.XLOOKUP(A24,'Hospitalisation Details'!$A$2:$A$2339,'Hospitalisation Details'!$M$2:$M$2339) -> 64 | R24: =IF(Q24<20, "Young",IF(Q24<40,"Adult",IF(Q24<60, "Middle Aged", "Senior"))) -> Senior
... A2336: Id2335 | B2336: =_xlfn.XLOOKUP(A2336,'Customer Names'!$A$2:$A$2336,'Customer Names'!$D$2:$D$2336) -> Aaron K | C2336: =_xlfn.XLOOKUP(A2336,'Midical Examination'!$A$2:$A$2336,'Midical Examination'!$B$2:$B$2336) -> 17.58 | D2336: =_xlfn.XLOOKUP(A2336,'Midical Examination'!$A$2:$A$2336,'Midical Examination'!$C$2:$C$2336) -> 4.51 | E2336: =_xlfn.XLOOKUP(A2336,'Midical Examination'!$A$2:$A$2336,'Midical Examination'!$D$2:$D$2336) -> No | F2336: =_xlfn.XLOOKUP(A2336,'Midical Examination'!$A$2:$A$2336,'Midical Examination'!$E$2:$E$2336) -> No | G2336: =_xlfn.XLOOKUP(A2336,'Midical Examination'!$A$2:$A$2336,'Midical Examination'!$F$2:$F$2336) -> No | H2336: =_xlfn.XLOOKUP(A2336,'Midical Examination'!$A$2:$A$2336,'Midical Examination'!$G$2:$G$2336) -> 1 | I2336: =_xlfn.XLOOKUP(A2336,'Midical Examination'!$A$2:$A$2336,'Midical Examination'!$H$2:$H$2336) -> No | J2336: =_xlfn.XLOOKUP(A2336,'Midical Examination'!$A$2:$A$2336,'Midical Examination'!$I$2:$I$2336) -> Underweight | K2336: =IF(D2336<5.7, "Normal", IF(D2336<6.5,"Pre-Diabetic", "Diabetic")) -> Normal | L2336: =_xlfn.XLOOKUP(A2336,'Hospitalisation Details'!$A$2:$A$2339,'Hospitalisation Details'!$L$2:$L$2339) -> 33794 | M2336: =_xlfn.XLOOKUP(A2336,'Hospitalisation Details'!$A$2:$A$2339,'Hospitalisation Details'!$F$2:$F$2339) -> 563.84 | N2336: =_xlfn.XLOOKUP(A2336,'Hospitalisation Details'!$A$2:$A$2339,'Hospitalisation Details'!$G$2:$G$2339) -> tier - 2 | O2336: =_xlfn.XLOOKUP(A2336,'Hospitalisation Details'!$A$2:$A$2339,'Hospitalisation Details'!$H$2:$H$2339) -> tier - 3 | P2336: =_xlfn.XLOOKUP(A2336,'Hospitalisation Details'!$A$2:$A$2339,'Hospitalisation Details'!$I$2:$I$2339) -> R1013 | Q2336: =_xlfn.XLOOKUP(A2336,'Hospitalisation Details'!$A$2:$A$2339,'Hospitalisation Details'!$M$2:$M$2339) -> 30 | R2336: =IF(Q2336<20, "Young",IF(Q2336<40,"Adult",IF(Q2336<60, "Middle Aged", "Senior"))) -> Adult
M2337: =SUM(M2:M2336) -> 31592359
M2338: =AVERAGE(M2:M2336) -> 13529.918

Sheet Dashboard Manual
A3: Count of Customer ID | B3: Column Labels
A4: Row Labels | B4: Yes | C4: Grand Total | N4: Insight for Smokers VS Non-Smokers Cancer Distribution
A5: No | B5: 307 | C5: 307 | N5: * Non-smokers have a much higher count of individuals with cancer history (1540) compared to smokers (404).
A6: yes | B6: 84 | C6: 84 | N6: * This shows that cancer history is more common among non-smokers in this dataset, possibly due to age or other risk factors.
A7: Grand Total | B7: 391 | C7: 391
N18: Insight for Charges by Weight Status
N19: * Obesity category has the highest total medical charges, far exceeding all other weight groups.
A20: Row Labels | B20: Sum of charges | N20: * Overweight individuals also show elevated costs, ranking second after obseity.
A21: Normal Weight | B21: 4305290.1 | N21: * Normal-weight patients have noticeably lower charges, indicating fewer health-related expenses.
A22: Obesity | B22: 20343647 | N22: * Underweight patients incur the least charges, suggesting minimal medical cost impact compared to others.
A23: Overweight | B23: 5729141.8
A24: Underweight | B24: 1214279.9
A25: Grand Total | B25: 31592359

Sheet Data_Visualization
F1: Average Charges by Hospital Tier
P3: Metric | T3: Value
P4: Average costs and medical metrics
P5: Average Charges | T5: 13529.92
P6: Average BMI | T6: 30.97
P7: Average HBA1C | T7: 6.579
B8: Row Labels | C8: Average of charges | P8: Average Age | T8: 39
B9: tier - 1 | C9: 30129.199 | P9: Average Surgeries | T9: 0.68
B10: tier - 2 | C10: 11865.269 | P10: Total healthcare costs | T10: 31592359
B11: tier - 3 | C11: 9462.2693 | P11: Total customers count | T11: 2335
B12: Grand Total | C12: 13529.918 | P12: Total hospitalisation count | T12: 2338
Q15: TITLE
Q16: 1 | R16: Average Patient Charges by Hospital Tier
Q17: 2 | R17: Weight Status Distribution of Patients
F18: Distribution of Weight Status | Q18: 3 | R18: Average HBA1C Levels by Diabetes Status
Q19: 4 | R19: Major Surgeries Count by Age Group
B20: Row Labels | C20: Count of Customer ID | Q20: 5 | R20: Cancer Incidence Across Age Groups
B21: Normal Weight | C21: 437
B22: Obesity | C22: 1221
B23: Overweight | C23: 501
B24: Underweight | C24: 176
B25: Grand Total | C25: 2335
F36: Average HBA1C by Diabetes Status
B37: Row Labels | C37: Average of HBA1C
B38: Diabetic | C38: 9.308699
B39: Normal | C39: 4.8492694
B40: Pre-Diabetic | C40: 6.0394518
B41: Grand Total | C41: 6.5789979
F54: Number of Surgeries by Age Group
B56: Row Labels | C56: Sum of Number Of Major Surgeries
B57: Adult | C57: 563
B58: Middle Aged | C58: 676
B59: Senior | C59: 160
B60: Young | C60: 180
B61: Grand Total | C61: 1579
F72: Cancer History vs Age
A76: Count of Customer ID | B76: Column Labels
A77: Row Labels | B77: No | C77: Yes | D77: Grand Total
A78: Adult | B78: 839 | C78: 152 | D78: 991
A79: Middle Aged | B79: 866 | C79: 155 | D79: 1021
A80: Senior | B80: 141 | C80: 2 | D80: 143
A81: Young | B81: 98 | C81: 82 | D81: 180
A82: Grand Total | B82: 1944 | C82: 391 | D82: 2335

Sheet Healthcare Dashboard
A1: Healthcare Dashboard – AI Analysis
U4: Count of Customer ID | V4: Column Labels
U5: Row Labels | V5: No | W5: Yes | X5: Grand Total
U6: No | V6: 1540 | W6: 307 | X6: 1847
U7: yes | V7: 404 | W7: 84 | X7: 488
U8: Grand Total | V8: 1944 | W8: 391 | X8: 2335
U10: Row Labels | V10: Sum of charges
U11: Normal Weight | V11: 4305290.1
U12: Obesity | V12: 20343647
U13: Overweight | V13: 5729141.8
U14: Underweight | V14: 1214279.9
U15: Grand Total | V15: 31592359
U19: Row Labels | V19: Average of charges
U20: tier - 1 | V20: 30129.199
U21: tier - 2 | V21: 11865.269
U22: tier - 3 | V22: 9462.2693
U23: Grand Total | V23: 13529.918
U26: Row Labels | V26: Count of Customer ID
U27: Normal Weight | V27: 437
U28: Obesity | V28: 1221
U29: Overweight | V29: 501
U30: Underweight | V30: 176
U31: Grand Total | V31: 2335
U35: Row Labels | V35: Average of HBA1C
U36: Diabetic | V36: 9.308699
U37: Normal | V37: 4.8492694
U38: Pre-Diabetic | V38: 6.0394518
U39: Grand Total | V39: 6.5789979
U42: Count of Customer ID | V42: Column Labels
U43: Row Labels | V43: No | W43: Yes | X43: Grand Total
U44: Adult | V44: 839 | W44: 152 | X44: 991
U45: Middle Aged | V45: 866 | W45: 155 | X45: 1021
U46: Senior | V46: 141 | W46: 2 | X46: 143
U47: Young | V47: 98 | W47: 82 | X47: 180
U48: Grand Total | V48: 1944 | W48: 391 | X48: 2335
U50: Row Labels | V50: Sum of Number Of Major Surgeries
U51: Adult | V51: 563
U52: Middle Aged | V52: 676
U53: Senior | V53: 160
U54: Young | V54: 180
U55: Grand Total | V55: 1579
